FDL26/FDL26_tests/ibex_csr/rtl/ibex_csr.sv
// Copyright lowRISC contributors.
// Licensed under the Apache License, Version 2.0, see LICENSE for details.
// SPDX-License-Identifier: Apache-2.0

/**
 * Control / status register primitive
 */

//`include "prim_assert.sv"

module ibex_csr #(
  parameter int unsigned    Width      = 32,
  parameter bit             ShadowCopy = 1'b0,
  parameter bit [Width-1:0] ResetValue = '0
 ) (
  input  logic             clk_i,
  input  logic             rst_ni,

  input  logic [Width-1:0] wr_data_i,
  input  logic             wr_en_i,
  output logic [Width-1:0] rd_data_o,

  output logic             rd_error_o
);

  logic [Width-1:0] rdata_q;

  always_ff @(posedge clk_i or negedge rst_ni) begin
    if (!rst_ni) begin
      rdata_q <= ResetValue;
    end else if (wr_en_i) begin
      rdata_q <= wr_data_i;
    end
  end

  assign rd_data_o = rdata_q;

  if (ShadowCopy) begin : gen_shadow
    logic [Width-1:0] shadow_q;

    always_ff @(posedge clk_i or negedge rst_ni) begin
      if (!rst_ni) begin
        shadow_q <= ~ResetValue;
      end else if (wr_en_i) begin
        shadow_q <= ~wr_data_i;
      end
    end

    assign rd_error_o = rdata_q != ~shadow_q;

  end else begin : gen_no_shadow
    assign rd_error_o = 1'b0;
  end

  //`ASSERT_KNOWN(IbexCSREnValid, wr_en_i)

endmodule

FDL26/FDL26_tests/ibex_csr/6_testbench_generator/testbench_wr_en_i.sv
`timescale 1ns/1ns

module test;

  localparam int unsigned WIDTH = 32;
  localparam bit SHADOW_COPY    = 1'b1;
  localparam logic [WIDTH-1:0] RESET_VALUE = 32'h0;
  localparam int NUM_TESTS = 100;



  logic clk;

  logic clk_i;

  logic rst_ni;

  logic [WIDTH-1:0] wr_data_i;

  logic wr_en_i;

  logic [WIDTH-1:0] rd_data_o;

  logic rd_error_o;


  // Device Under Test (DUT)

  ibex_csr #(
    .Width(WIDTH),
    .ShadowCopy(SHADOW_COPY),
    .ResetValue(RESET_VALUE)
  ) dut(
    .clk_i(clk),
    .rst_ni(rst_ni),
    .wr_data_i(wr_data_i),
    .wr_en_i(wr_en_i),
    .rd_data_o(rd_data_o),
    .rd_error_o(rd_error_o)
  );


  always #5 clk = ~clk;


  initial begin

    $dumpfile("ibex_csr.vcd");

    $dumpvars(0, test);

    clk = 0;

    rst_ni = 0;

    wr_data_i = 0;

    wr_en_i = 0;

    #0 wr_data_i = 0;

    #10 rst_ni = 1;

    #10;

    rst_ni = 1;

    wr_data_i = 16843009;

    wr_en_i = 1;

    #10 wr_en_i = 0;

    #0 wr_data_i = 0;

    #5 rst_ni = 0;

    #5;

    rst_ni = 1;

    wr_data_i = 33686018;

    wr_en_i = 1;

    #10 wr_en_i = 0;

    #0 wr_data_i = 0;

    #5 rst_ni = 0;

    #5;

    rst_ni = 1;

    wr_data_i = 50529027;

    wr_en_i = 1;

    #10 wr_en_i = 0;

    #0 wr_data_i = 0;

    #5 rst_ni = 0;

    #5;

    rst_ni = 1;

    wr_data_i = 67372036;

    wr_en_i = 1;

    #10 wr_en_i = 0;

    #0 wr_data_i = 0;

    #5 rst_ni = 0;

    #5;

    rst_ni = 1;

    wr_data_i = 84215045;

    wr_en_i = 1;

    #10 wr_en_i = 0;

    #0 wr_data_i = 0;

    #5 rst_ni = 0;

    #5;

    rst_ni = 1;

    wr_data_i = 101058054;

    wr_en_i = 1;

    #10 wr_en_i = 0;

    #0 wr_data_i = 0;

    #5 rst_ni = 0;

    #5;

    rst_ni = 1;

    wr_data_i = 117901063;

    wr_en_i = 1;

    #10 wr_en_i = 0;

    #0 wr_data_i = 0;

    #5 rst_ni = 0;

    #5;

    rst_ni = 1;

    wr_data_i = 134744072;

    wr_en_i = 1;

    #10 wr_en_i = 0;

    #0 wr_data_i = 0;

    #5 rst_ni = 0;

    #5;

    rst_ni = 1;

    wr_data_i = 151587081;

    wr_en_i = 1;

    #10 wr_en_i = 0;

    #0 wr_data_i = 0;

    #5 rst_ni = 0;

    #5;

    rst_ni = 1;

    wr_data_i = 168430090;

    wr_en_i = 1;

    #10 wr_en_i = 0;

    #0 wr_data_i = 0;

    #5 rst_ni = 0;

    #5;

    rst_ni = 1;

    wr_data_i = 185273099;

    wr_en_i = 1;

    #10 wr_en_i = 0;

    #0 wr_data_i = 0;

    #5 rst_ni = 0;

    #5;

    rst_ni = 1;

    wr_data_i = 202116108;

    wr_en_i = 1;

    #10 wr_en_i = 0;

    #0 wr_data_i = 0;

    #5 rst_ni = 0;

    #5;

    rst_ni = 1;

    wr_data_i = 218959117;

    wr_en_i = 1;

    #10 wr_en_i = 0;

    #0 wr_data_i = 0;

    #5 rst_ni = 0;

    #5;

    rst_ni = 1;

    wr_data_i = 235802126;

    wr_en_i = 1;

    #10 wr_en_i = 0;

    #0 wr_data_i = 0;

    #5 rst_ni = 0;

    #5;

    rst_ni = 1;

    wr_data_i = 252645135;

    wr_en_i = 1;

    #10 wr_en_i = 0;

    #0 wr_data_i = 0;

    #5 rst_ni = 0;

    #5;

    rst_ni = 1;

    wr_data_i = 269488144;

    wr_en_i = 1;

    #10 wr_en_i = 0;

    #0 wr_data_i = 0;

    #5 rst_ni = 0;

    #5;

    rst_ni = 1;

    wr_data_i = 286331153;

    wr_en_i = 1;

    #10 wr_en_i = 0;

    #0 wr_data_i = 0;

    #5 rst_ni = 0;

    #5;

    rst_ni = 1;

    wr_data_i = 303174162;

    wr_en_i = 1;

    #10 wr_en_i = 0;

    #0 wr_data_i = 0;

    #5 rst_ni = 0;

    #5;

    rst_ni = 1;

    wr_data_i = 320017171;

    wr_en_i = 1;

    #10 wr_en_i = 0;

    #0 wr_data_i = 0;

    #5 rst_ni = 0;

    #5;

    rst_ni = 1;

    wr_data_i = 336860180;

    wr_en_i = 1;

    #10 wr_en_i = 0;

    #0 wr_data_i = 0;

    #5 rst_ni = 0;

    #5;

    rst_ni = 1;

    wr_data_i = 353703189;

    wr_en_i = 1;

    #10 wr_en_i = 0;

    #0 wr_data_i = 0;

    #5 rst_ni = 0;

    #5;

    rst_ni = 1;

    wr_data_i = 370546198;

    wr_en_i = 1;

    #10 wr_en_i = 0;

    #0 wr_data_i = 0;

    #5 rst_ni = 0;

    #5;

    rst_ni = 1;

    wr_data_i = 387389207;

    wr_en_i = 1;

    #10 wr_en_i = 0;

    #0 wr_data_i = 0;

    #5 rst_ni = 0;

    #5;

    rst_ni = 1;

    wr_data_i = 404232216;

    wr_en_i = 1;

    #10 wr_en_i = 0;

    #0 wr_data_i = 0;

    #5 rst_ni = 0;

    #5;

    rst_ni = 1;

    wr_data_i = 421075225;

    wr_en_i = 1;

    #10 wr_en_i = 0;

    #0 wr_data_i = 0;

    #5 rst_ni = 0;

    #5;

    rst_ni = 1;

    wr_data_i = 437918234;

    wr_en_i = 1;

    #10 wr_en_i = 0;

    #0 wr_data_i = 0;

    #5 rst_ni = 0;

    #5;

    rst_ni = 1;

    wr_data_i = 454761243;

    wr_en_i = 1;

    #10 wr_en_i = 0;

    #0 wr_data_i = 0;

    #5 rst_ni = 0;

    #5;

    rst_ni = 1;

    wr_data_i = 471604252;

    wr_en_i = 1;

    #10 wr_en_i = 0;

    #0 wr_data_i = 0;

    #5 rst_ni = 0;

    #5;

    rst_ni = 1;

    wr_data_i = 488447261;

    wr_en_i = 1;

    #10 wr_en_i = 0;

    #0 wr_data_i = 0;

    #5 rst_ni = 0;

    #5;

    rst_ni = 1;

    wr_data_i = 505290270;

    wr_en_i = 1;

    #10 wr_en_i = 0;

    #0 wr_data_i = 0;

    #5 rst_ni = 0;

    #5;

    rst_ni = 1;

    wr_data_i = 522133279;

    wr_en_i = 1;

    #10 wr_en_i = 0;

    #0 wr_data_i = 0;

    #5 rst_ni = 0;

    #5;

    rst_ni = 1;

    wr_data_i = 538976288;

    wr_en_i = 1;

    #10 wr_en_i = 0;

    #0 wr_data_i = 0;

    #5 rst_ni = 0;

    #5;

    rst_ni = 1;

    wr_data_i = 555819297;

    wr_en_i = 1;

    #10 wr_en_i = 0;

    #0 wr_data_i = 0;

    #5 rst_ni = 0;

    #5;

    rst_ni = 1;

    wr_data_i = 572662306;

    wr_en_i = 1;

    #10 wr_en_i = 0;

    #0 wr_data_i = 0;

    #5 rst_ni = 0;

    #5;

    rst_ni = 1;

    wr_data_i = 589505315;

    wr_en_i = 1;

    #10 wr_en_i = 0;

    #0 wr_data_i = 0;

    #5 rst_ni = 0;

    #5;

    rst_ni = 1;

    wr_data_i = 606348324;

    wr_en_i = 1;

    #10 wr_en_i = 0;

    #0 wr_data_i = 0;

    #5 rst_ni = 0;

    #5;

    rst_ni = 1;

    wr_data_i = 623191333;

    wr_en_i = 1;

    #10 wr_en_i = 0;

    #0 wr_data_i = 0;

    #5 rst_ni = 0;

    #5;

    rst_ni = 1;

    wr_data_i = 640034342;

    wr_en_i = 1;

    #10 wr_en_i = 0;

    #0 wr_data_i = 0;

    #5 rst_ni = 0;

    #5;

    rst_ni = 1;

    wr_data_i = 656877351;

    wr_en_i = 1;

    #10 wr_en_i = 0;

    #0 wr_data_i = 0;

    #5 rst_ni = 0;

    #5;

    rst_ni = 1;

    wr_data_i = 673720360;

    wr_en_i = 1;

    #10 wr_en_i = 0;

    #0 wr_data_i = 0;

    #5 rst_ni = 0;

    #5;

    rst_ni = 1;

    wr_data_i = 690563369;

    wr_en_i = 1;

    #10 wr_en_i = 0;

    #0 wr_data_i = 0;

    #5 rst_ni = 0;

    #5;

    rst_ni = 1;

    wr_data_i = 707406378;

    wr_en_i = 1;

    #10 wr_en_i = 0;

    #0 wr_data_i = 0;

    #5 rst_ni = 0;

    #5;

    rst_ni = 1;

    wr_data_i = 724249387;

    wr_en_i = 1;

    #10 wr_en_i = 0;

    #0 wr_data_i = 0;

    #5 rst_ni = 0;

    #5;

    rst_ni = 1;

    wr_data_i = 741092396;

    wr_en_i = 1;

    #10 wr_en_i = 0;

    #0 wr_data_i = 0;

    #5 rst_ni = 0;

    #5;

    rst_ni = 1;

    wr_data_i = 757935405;

    wr_en_i = 1;

    #10 wr_en_i = 0;

    #0 wr_data_i = 0;

    #5 rst_ni = 0;

    #5;

    rst_ni = 1;

    wr_data_i = 774778414;

    wr_en_i = 1;

    #10 wr_en_i = 0;

    #0 wr_data_i = 0;

    #5 rst_ni = 0;

    #5;

    rst_ni = 1;

    wr_data_i = 791621423;

    wr_en_i = 1;

    #10 wr_en_i = 0;

    #0 wr_data_i = 0;

    #5 rst_ni = 0;

    #5;

    rst_ni = 1;

    wr_data_i = 808464432;

    wr_en_i = 1;

    #10 wr_en_i = 0;

    #0 wr_data_i = 0;

    #5 rst_ni = 0;

    #5;

    rst_ni = 1;

    wr_data_i = 825307441;

    wr_en_i = 1;

    #10 wr_en_i = 0;

    #0 wr_data_i = 0;

    #5 rst_ni = 0;

    #5;

    rst_ni = 1;

    wr_data_i = 842150450;

    wr_en_i = 1;

    #10 wr_en_i = 0;

    #0 wr_data_i = 0;

    #5 rst_ni = 0;

    #5;

    rst_ni = 1;

    wr_data_i = 858993459;

    wr_en_i = 1;

    #10 wr_en_i = 0;

    #0 wr_data_i = 0;

    #5 rst_ni = 0;

    #5;

    rst_ni = 1;

    wr_data_i = 875836468;

    wr_en_i = 1;

    #10 wr_en_i = 0;

    #0 wr_data_i = 0;

    #5 rst_ni = 0;

    #5;

    rst_ni = 1;

    wr_data_i = 892679477;

    wr_en_i = 1;

    #10 wr_en_i = 0;

    #0 wr_data_i = 0;

    #5 rst_ni = 0;

    #5;

    rst_ni = 1;

    wr_data_i = 909522486;

    wr_en_i = 1;

    #10 wr_en_i = 0;

    #0 wr_data_i = 0;

    #5 rst_ni = 0;

    #5;

    rst_ni = 1;

    wr_data_i = 926365495;

    wr_en_i = 1;

    #10 wr_en_i = 0;

    #0 wr_data_i = 0;

    #5 rst_ni = 0;

    #5;

    rst_ni = 1;

    wr_data_i = 943208504;

    wr_en_i = 1;

    #10 wr_en_i = 0;

    #0 wr_data_i = 0;

    #5 rst_ni = 0;

    #5;

    rst_ni = 1;

    wr_data_i = 960051513;

    wr_en_i = 1;

    #10 wr_en_i = 0;

    #0 wr_data_i = 0;

    #5 rst_ni = 0;

    #5;

    rst_ni = 1;

    wr_data_i = 976894522;

    wr_en_i = 1;

    #10 wr_en_i = 0;

    #0 wr_data_i = 0;

    #5 rst_ni = 0;

    #5;

    rst_ni = 1;

    wr_data_i = 993737531;

    wr_en_i = 1;

    #10 wr_en_i = 0;

    #0 wr_data_i = 0;

    #5 rst_ni = 0;

    #5;

    rst_ni = 1;

    wr_data_i = 1010580540;

    wr_en_i = 1;

    #10 wr_en_i = 0;

    #0 wr_data_i = 0;

    #5 rst_ni = 0;

    #5;

    rst_ni = 1;

    wr_data_i = 1027423549;

    wr_en_i = 1;

    #10 wr_en_i = 0;

    #0 wr_data_i = 0;

    #5 rst_ni = 0;

    #5;

    rst_ni = 1;

    wr_data_i = 1044266558;

    wr_en_i = 1;

    #10 wr_en_i = 0;

    #0 wr_data_i = 0;

    #5 rst_ni = 0;

    #5;

    rst_ni = 1;

    wr_data_i = 1061109567;

    wr_en_i = 1;

    #10 wr_en_i = 0;

    #0 wr_data_i = 0;

    #5 rst_ni = 0;

    #5;

    rst_ni = 1;

    wr_data_i = 1077952576;

    wr_en_i = 1;

    #10 wr_en_i = 0;

    #0 wr_data_i = 0;

    #5 rst_ni = 0;

    #5;

    rst_ni = 1;

    wr_data_i = 1094795585;

    wr_en_i = 1;

    #10 wr_en_i = 0;

    #0 wr_data_i = 0;

    #5 rst_ni = 0;

    #5;

    rst_ni = 1;

    wr_data_i = 1111638594;

    wr_en_i = 1;

    #10 wr_en_i = 0;

    #0 wr_data_i = 0;

    #5 rst_ni = 0;

    #5;

    rst_ni = 1;

    wr_data_i = 1128481603;

    wr_en_i = 1;

    #10 wr_en_i = 0;

    #0 wr_data_i = 0;

    #5 rst_ni = 0;

    #5;

    rst_ni = 1;

    wr_data_i = 1145324612;

    wr_en_i = 1;

    #10 wr_en_i = 0;

    #0 wr_data_i = 0;

    #5 rst_ni = 0;

    #5;

    rst_ni = 1;

    wr_data_i = 1162167621;

    wr_en_i = 1;

    #10 wr_en_i = 0;

    #0 wr_data_i = 0;

    #5 rst_ni = 0;

    #5;

    rst_ni = 1;

    wr_data_i = 1179010630;

    wr_en_i = 1;

    #10 wr_en_i = 0;

    #0 wr_data_i = 0;

    #5 rst_ni = 0;

    #5;

    rst_ni = 1;

    wr_data_i = 1195853639;

    wr_en_i = 1;

    #10 wr_en_i = 0;

    #0 wr_data_i = 0;

    #5 rst_ni = 0;

    #5;

    rst_ni = 1;

    wr_data_i = 1212696648;

    wr_en_i = 1;

    #10 wr_en_i = 0;

    #0 wr_data_i = 0;

    #5 rst_ni = 0;

    #5;

    rst_ni = 1;

    wr_data_i = 1229539657;

    wr_en_i = 1;

    #10 wr_en_i = 0;

    #0 wr_data_i = 0;

    #5 rst_ni = 0;

    #5;

    rst_ni = 1;

    wr_data_i = 1246382666;

    wr_en_i = 1;

    #10 wr_en_i = 0;

    #0 wr_data_i = 0;

    #5 rst_ni = 0;

    #5;

    rst_ni = 1;

    wr_data_i = 1263225675;

    wr_en_i = 1;

    #10 wr_en_i = 0;

    #0 wr_data_i = 0;

    #5 rst_ni = 0;

    #5;

    rst_ni = 1;

    wr_data_i = 1280068684;

    wr_en_i = 1;

    #10 wr_en_i = 0;

    #0 wr_data_i = 0;

    #5 rst_ni = 0;

    #5;

    rst_ni = 1;

    wr_data_i = 1296911693;

    wr_en_i = 1;

    #10 wr_en_i = 0;

    #0 wr_data_i = 0;

    #5 rst_ni = 0;

    #5;

    rst_ni = 1;

    wr_data_i = 1313754702;

    wr_en_i = 1;

    #10 wr_en_i = 0;

    #0 wr_data_i = 0;

    #5 rst_ni = 0;

    #5;

    rst_ni = 1;

    wr_data_i = 1330597711;

    wr_en_i = 1;

    #10 wr_en_i = 0;

    #0 wr_data_i = 0;

    #5 rst_ni = 0;

    #5;

    rst_ni = 1;

    wr_data_i = 1347440720;

    wr_en_i = 1;

    #10 wr_en_i = 0;

    #0 wr_data_i = 0;

    #5 rst_ni = 0;

    #5;

    rst_ni = 1;

    wr_data_i = 1364283729;

    wr_en_i = 1;

    #10 wr_en_i = 0;

    #0 wr_data_i = 0;

    #5 rst_ni = 0;

    #5;

    rst_ni = 1;

    wr_data_i = 1381126738;

    wr_en_i = 1;

    #10 wr_en_i = 0;

    #0 wr_data_i = 0;

    #5 rst_ni = 0;

    #5;

    rst_ni = 1;

    wr_data_i = 1397969747;

    wr_en_i = 1;

    #10 wr_en_i = 0;

    #0 wr_data_i = 0;

    #5 rst_ni = 0;

    #5;

    rst_ni = 1;

    wr_data_i = 1414812756;

    wr_en_i = 1;

    #10 wr_en_i = 0;

    #0 wr_data_i = 0;

    #5 rst_ni = 0;

    #5;

    rst_ni = 1;

    wr_data_i = 1431655765;

    wr_en_i = 1;

    #10 wr_en_i = 0;

    #0 wr_data_i = 0;

    #5 rst_ni = 0;

    #5;

    rst_ni = 1;

    wr_data_i = 1448498774;

    wr_en_i = 1;

    #10 wr_en_i = 0;

    #0 wr_data_i = 0;

    #5 rst_ni = 0;

    #5;

    rst_ni = 1;

    wr_data_i = 1465341783;

    wr_en_i = 1;

    #10 wr_en_i = 0;

    #0 wr_data_i = 0;

    #5 rst_ni = 0;

    #5;

    rst_ni = 1;

    wr_data_i = 1482184792;

    wr_en_i = 1;

    #10 wr_en_i = 0;

    #0 wr_data_i = 0;

    #5 rst_ni = 0;

    #5;

    rst_ni = 1;

    wr_data_i = 1499027801;

    wr_en_i = 1;

    #10 wr_en_i = 0;

    #0 wr_data_i = 0;

    #5 rst_ni = 0;

    #5;

    rst_ni = 1;

    wr_data_i = 1515870810;

    wr_en_i = 1;

    #10 wr_en_i = 0;

    #0 wr_data_i = 0;

    #5 rst_ni = 0;

    #5;

    rst_ni = 1;

    wr_data_i = 1532713819;

    wr_en_i = 1;

    #10 wr_en_i = 0;

    #0 wr_data_i = 0;

    #5 rst_ni = 0;

    #5;

    rst_ni = 1;

    wr_data_i = 1549556828;

    wr_en_i = 1;

    #10 wr_en_i = 0;

    #0 wr_data_i = 0;

    #5 rst_ni = 0;

    #5;

    rst_ni = 1;

    wr_data_i = 1566399837;

    wr_en_i = 1;

    #10 wr_en_i = 0;

    #0 wr_data_i = 0;

    #5 rst_ni = 0;

    #5;

    rst_ni = 1;

    wr_data_i = 1583242846;

    wr_en_i = 1;

    #10 wr_en_i = 0;

    #0 wr_data_i = 0;

    #5 rst_ni = 0;

    #5;

    rst_ni = 1;

    wr_data_i = 1600085855;

    wr_en_i = 1;

    #10 wr_en_i = 0;

    #0 wr_data_i = 0;

    #5 rst_ni = 0;

    #5;

    rst_ni = 1;

    wr_data_i = 1616928864;

    wr_en_i = 1;

    #10 wr_en_i = 0;

    #0 wr_data_i = 0;

    #5 rst_ni = 0;

    #5;

    rst_ni = 1;

    wr_data_i = 1633771873;

    wr_en_i = 1;

    #10 wr_en_i = 0;

    #0 wr_data_i = 0;

    #5 rst_ni = 0;

    #5;

    rst_ni = 1;

    wr_data_i = 1650614882;

    wr_en_i = 1;

    #10 wr_en_i = 0;

    #0 wr_data_i = 0;

    #5 rst_ni = 0;

    #5;

    rst_ni = 1;

    wr_data_i = 1667457891;

    wr_en_i = 1;

    #10 wr_en_i = 0;

    #0 wr_data_i = 0;

    #5 rst_ni = 0;

    #5;

    #50;

    $finish;
  end
endmodule

DATE_tests/ibex_csr/6_testbench_generator/ibex_csr.vcd
$date
	Mon Aug 25 17:29:17 2025
$end
$version
	ModelSim Version 2019.4
$end
$timescale
	1ns
$end

$scope module test $end
$var parameter 32 ! WIDTH $end
$var parameter 1 " SHADOW_COPY $end
$var parameter 32 # RESET_VALUE $end
$var parameter 32 $ NUM_TESTS $end
$var reg 1 % clk $end
$var reg 1 & clk_i $end
$var reg 1 ' rst_ni $end
$var reg 32 ( wr_data_i [31:0] $end
$var reg 1 ) wr_en_i $end
$var reg 32 * rd_data_o [31:0] $end
$var reg 1 + rd_error_o $end

$scope module dut $end
$var parameter 32 , Width $end
$var parameter 1 - ShadowCopy $end
$var parameter 32 . ResetValue $end
$var wire 1 / clk_i $end
$var wire 1 0 rst_ni $end
$var wire 1 1 wr_data_i [31] $end
$var wire 1 2 wr_data_i [30] $end
$var wire 1 3 wr_data_i [29] $end
$var wire 1 4 wr_data_i [28] $end
$var wire 1 5 wr_data_i [27] $end
$var wire 1 6 wr_data_i [26] $end
$var wire 1 7 wr_data_i [25] $end
$var wire 1 8 wr_data_i [24] $end
$var wire 1 9 wr_data_i [23] $end
$var wire 1 : wr_data_i [22] $end
$var wire 1 ; wr_data_i [21] $end
$var wire 1 < wr_data_i [20] $end
$var wire 1 = wr_data_i [19] $end
$var wire 1 > wr_data_i [18] $end
$var wire 1 ? wr_data_i [17] $end
$var wire 1 @ wr_data_i [16] $end
$var wire 1 A wr_data_i [15] $end
$var wire 1 B wr_data_i [14] $end
$var wire 1 C wr_data_i [13] $end
$var wire 1 D wr_data_i [12] $end
$var wire 1 E wr_data_i [11] $end
$var wire 1 F wr_data_i [10] $end
$var wire 1 G wr_data_i [9] $end
$var wire 1 H wr_data_i [8] $end
$var wire 1 I wr_data_i [7] $end
$var wire 1 J wr_data_i [6] $end
$var wire 1 K wr_data_i [5] $end
$var wire 1 L wr_data_i [4] $end
$var wire 1 M wr_data_i [3] $end
$var wire 1 N wr_data_i [2] $end
$var wire 1 O wr_data_i [1] $end
$var wire 1 P wr_data_i [0] $end
$var wire 1 Q wr_en_i $end
$var reg 32 R rd_data_o [31:0] $end
$var reg 1 S rd_error_o $end
$var reg 32 T rdata_q [31:0] $end

$scope begin gen_shadow $end
$var reg 32 U shadow_q [31:0] $end
$upscope $end
$upscope $end
$upscope $end
$enddefinitions $end
#0
$dumpvars
0%
x&
0'
b0 (
0)
b0 *
0+
b0 R
0S
b0 T
b11111111111111111111111111111111 U
b100000 !
b1 "
b0 #
b1100100 $
b100000 ,
b1 -
b0 .
0Q
0P
0O
0N
0M
0L
0K
0J
0I
0H
0G
0F
0E
0D
0C
0B
0A
0@
0?
0>
0=
0<
0;
0:
09
08
07
06
05
04
03
02
01
00
0/
$end
#5
1%
1/
#10
1'
0%
10
0/
#15
1%
1/
#20
b1000000010000000100000001 (
1)
0%
1P
1H
1@
18
1Q
0/
#25
1%
1/
b1000000010000000100000001 T
b11111110111111101111111011111110 U
b1000000010000000100000001 R
b1000000010000000100000001 *
#30
0)
0%
0Q
0/
b0 (
0P
0H
0@
08
#35
1%
0'
1/
00
b0 T
b11111111111111111111111111111111 U
b0 R
b0 *
#40
0%
1'
b10000000100000001000000010 (
1)
1O
1G
1?
17
1Q
0/
10
#45
1%
1/
b10000000100000001000000010 T
b11111101111111011111110111111101 U
b10000000100000001000000010 R
b10000000100000001000000010 *
#50
0)
0%
0Q
0/
b0 (
0O
0G
0?
07
#55
1%
0'
1/
00
b0 T
b11111111111111111111111111111111 U
b0 R
b0 *
#60
0%
1'
b11000000110000001100000011 (
1)
1P
1O
1H
1G
1@
1?
18
17
1Q
0/
10
#65
1%
1/
b11000000110000001100000011 T
b11111100111111001111110011111100 U
b11000000110000001100000011 R
b11000000110000001100000011 *
#70
0)
0%
0Q
0/
b0 (
0P
0O
0H
0G
0@
0?
08
07
#75
1%
0'
1/
00
b0 T
b11111111111111111111111111111111 U
b0 R
b0 *
#80
0%
1'
b100000001000000010000000100 (
1)
1N
1F
1>
16
1Q
0/
10
#85
1%
1/
b100000001000000010000000100 T
b11111011111110111111101111111011 U
b100000001000000010000000100 R
b100000001000000010000000100 *
#90
0)
0%
0Q
0/
b0 (
0N
0F
0>
06
#95
1%
0'
1/
00
b0 T
b11111111111111111111111111111111 U
b0 R
b0 *
#100
0%
1'
b101000001010000010100000101 (
1)
1P
1N
1H
1F
1@
1>
18
16
1Q
0/
10
#105
1%
1/
b101000001010000010100000101 T
b11111010111110101111101011111010 U
b101000001010000010100000101 R
b101000001010000010100000101 *
#110
0)
0%
0Q
0/
b0 (
0P
0N
0H
0F
0@
0>
08
06
#115
1%
0'
1/
00
b0 T
b11111111111111111111111111111111 U
b0 R
b0 *
#120
0%
1'
b110000001100000011000000110 (
1)
1O
1N
1G
1F
1?
1>
17
16
1Q
0/
10
#125
1%
1/
b110000001100000011000000110 T
b11111001111110011111100111111001 U
b110000001100000011000000110 R
b110000001100000011000000110 *
#130
0)
0%
0Q
0/
b0 (
0O
0N
0G
0F
0?
0>
07
06
#135
1%
0'
1/
00
b0 T
b11111111111111111111111111111111 U
b0 R
b0 *
#140
0%
1'
b111000001110000011100000111 (
1)
1P
1O
1N
1H
1G
1F
1@
1?
1>
18
17
16
1Q
0/
10
#145
1%
1/
b111000001110000011100000111 T
b11111000111110001111100011111000 U
b111000001110000011100000111 R
b111000001110000011100000111 *
#150
0)
0%
0Q
0/
b0 (
0P
0O
0N
0H
0G
0F
0@
0?
0>
08
07
06
#155
1%
0'
1/
00
b0 T
b11111111111111111111111111111111 U
b0 R
b0 *
#160
0%
1'
b1000000010000000100000001000 (
1)
1M
1E
1=
15
1Q
0/
10
#165
1%
1/
b1000000010000000100000001000 T
b11110111111101111111011111110111 U
b1000000010000000100000001000 R
b1000000010000000100000001000 *
#170
0)
0%
0Q
0/
b0 (
0M
0E
0=
05
#175
1%
0'
1/
00
b0 T
b11111111111111111111111111111111 U
b0 R
b0 *
#180
0%
1'
b1001000010010000100100001001 (
1)
1P
1M
1H
1E
1@
1=
18
15
1Q
0/
10
#185
1%
1/
b1001000010010000100100001001 T
b11110110111101101111011011110110 U
b1001000010010000100100001001 R
b1001000010010000100100001001 *
#190
0)
0%
0Q
0/
b0 (
0P
0M
0H
0E
0@
0=
08
05
#195
1%
0'
1/
00
b0 T
b11111111111111111111111111111111 U
b0 R
b0 *
#200
0%
1'
b1010000010100000101000001010 (
1)
1O
1M
1G
1E
1?
1=
17
15
1Q
0/
10
#205
1%
1/
b1010000010100000101000001010 T
b11110101111101011111010111110101 U
b1010000010100000101000001010 R
b1010000010100000101000001010 *
#210
0)
0%
0Q
0/
b0 (
0O
0M
0G
0E
0?
0=
07
05
#215
1%
0'
1/
00
b0 T
b11111111111111111111111111111111 U
b0 R
b0 *
#220
0%
1'
b1011000010110000101100001011 (
1)
1P
1O
1M
1H
1G
1E
1@
1?
1=
18
17
15
1Q
0/
10
#225
1%
1/
b1011000010110000101100001011 T
b11110100111101001111010011110100 U
b1011000010110000101100001011 R
b1011000010110000101100001011 *
#230
0)
0%
0Q
0/
b0 (
0P
0O
0M
0H
0G
0E
0@
0?
0=
08
07
05
#235
1%
0'
1/
00
b0 T
b11111111111111111111111111111111 U
b0 R
b0 *
#240
0%
1'
b1100000011000000110000001100 (
1)
1N
1M
1F
1E
1>
1=
16
15
1Q
0/
10
#245
1%
1/
b1100000011000000110000001100 T
b11110011111100111111001111110011 U
b1100000011000000110000001100 R
b1100000011000000110000001100 *
#250
0)
0%
0Q
0/
b0 (
0N
0M
0F
0E
0>
0=
06
05
#255
1%
0'
1/
00
b0 T
b11111111111111111111111111111111 U
b0 R
b0 *
#260
0%
1'
b1101000011010000110100001101 (
1)
1P
1N
1M
1H
1F
1E
1@
1>
1=
18
16
15
1Q
0/
10
#265
1%
1/
b1101000011010000110100001101 T
b11110010111100101111001011110010 U
b1101000011010000110100001101 R
b1101000011010000110100001101 *
#270
0)
0%
0Q
0/
b0 (
0P
0N
0M
0H
0F
0E
0@
0>
0=
08
06
05
#275
1%
0'
1/
00
b0 T
b11111111111111111111111111111111 U
b0 R
b0 *
#280
0%
1'
b1110000011100000111000001110 (
1)
1O
1N
1M
1G
1F
1E
1?
1>
1=
17
16
15
1Q
0/
10
#285
1%
1/
b1110000011100000111000001110 T
b11110001111100011111000111110001 U
b1110000011100000111000001110 R
b1110000011100000111000001110 *
#290
0)
0%
0Q
0/
b0 (
0O
0N
0M
0G
0F
0E
0?
0>
0=
07
06
05
#295
1%
0'
1/
00
b0 T
b11111111111111111111111111111111 U
b0 R
b0 *
#300
0%
1'
b1111000011110000111100001111 (
1)
1P
1O
1N
1M
1H
1G
1F
1E
1@
1?
1>
1=
18
17
16
15
1Q
0/
10
#305
1%
1/
b1111000011110000111100001111 T
b11110000111100001111000011110000 U
b1111000011110000111100001111 R
b1111000011110000111100001111 *
#310
0)
0%
0Q
0/
b0 (
0P
0O
0N
0M
0H
0G
0F
0E
0@
0?
0>
0=
08
07
06
05
#315
1%
0'
1/
00
b0 T
b11111111111111111111111111111111 U
b0 R
b0 *
#320
0%
1'
b10000000100000001000000010000 (
1)
1L
1D
1<
14
1Q
0/
10
#325
1%
1/
b10000000100000001000000010000 T
b11101111111011111110111111101111 U
b10000000100000001000000010000 R
b10000000100000001000000010000 *
#330
0)
0%
0Q
0/
b0 (
0L
0D
0<
04
#335
1%
0'
1/
00
b0 T
b11111111111111111111111111111111 U
b0 R
b0 *
#340
0%
1'
b10001000100010001000100010001 (
1)
1P
1L
1H
1D
1@
1<
18
14
1Q
0/
10
#345
1%
1/
b10001000100010001000100010001 T
b11101110111011101110111011101110 U
b10001000100010001000100010001 R
b10001000100010001000100010001 *
#350
0)
0%
0Q
0/
b0 (
0P
0L
0H
0D
0@
0<
08
04
#355
1%
0'
1/
00
b0 T
b11111111111111111111111111111111 U
b0 R
b0 *
#360
0%
1'
b10010000100100001001000010010 (
1)
1O
1L
1G
1D
1?
1<
17
14
1Q
0/
10
#365
1%
1/
b10010000100100001001000010010 T
b11101101111011011110110111101101 U
b10010000100100001001000010010 R
b10010000100100001001000010010 *
#370
0)
0%
0Q
0/
b0 (
0O
0L
0G
0D
0?
0<
07
04
#375
1%
0'
1/
00
b0 T
b11111111111111111111111111111111 U
b0 R
b0 *
