FDL26/FDL26_tests/ibex_csr/rtl/ibex_csr.sv
// Copyright lowRISC contributors.
// Licensed under the Apache License, Version 2.0, see LICENSE for details.
// SPDX-License-Identifier: Apache-2.0

/**
 * Control / status register primitive
 */

//`include "prim_assert.sv"

module ibex_csr #(
  parameter int unsigned    Width      = 32,
  parameter bit             ShadowCopy = 1'b0,
  parameter bit [Width-1:0] ResetValue = '0
 ) (
  input  logic             clk_i,
  input  logic             rst_ni,

  input  logic [Width-1:0] wr_data_i,
  input  logic             wr_en_i,
  output logic [Width-1:0] rd_data_o,

  output logic             rd_error_o
);

  logic [Width-1:0] rdata_q;

  always_ff @(posedge clk_i or negedge rst_ni) begin
    if (!rst_ni) begin
      rdata_q <= ResetValue;
    end else if (wr_en_i) begin
      rdata_q <= wr_data_i;
    end
  end

  assign rd_data_o = rdata_q;

  if (ShadowCopy) begin : gen_shadow
    logic [Width-1:0] shadow_q;

    always_ff @(posedge clk_i or negedge rst_ni) begin
      if (!rst_ni) begin
        shadow_q <= ~ResetValue;
      end else if (wr_en_i) begin
        shadow_q <= ~wr_data_i;
      end
    end

    assign rd_error_o = rdata_q != ~shadow_q;

  end else begin : gen_no_shadow
    assign rd_error_o = 1'b0;
  end

  //`ASSERT_KNOWN(IbexCSREnValid, wr_en_i)

endmodule

legacy/fdl26/FDL26/FDL26_tests/ibex_csr/tb/tb_ibex_csr.sv
module tb_ibex_csr;

  // Parametri
  localparam int unsigned WIDTH = 32;
  localparam bit SHADOW_COPY    = 1'b1;
  localparam logic [WIDTH-1:0] RESET_VALUE = 32'h0;
  localparam int NUM_TESTS = 100;

  // Segnali
  logic clk;
  logic rst_n;
  logic [WIDTH-1:0] wr_data;
  logic wr_en;
  logic [WIDTH-1:0] rd_data;
  logic rd_error;

  // Clock generation
  always #5 clk = ~clk;

  // DUT instantiation
  ibex_csr #(
    .Width(WIDTH),
    .ShadowCopy(SHADOW_COPY),
    .ResetValue(RESET_VALUE)
  ) dut (
    .clk_i(clk),
    .rst_ni(rst_n),
    .wr_data_i(wr_data),
    .wr_en_i(wr_en),
    .rd_data_o(rd_data),
    .rd_error_o(rd_error)
  );

  // Test sequence
  initial begin
    $dumpfile("ibex_csr.vcd");
    $dumpvars(0, tb_ibex_csr);

    $display("=== Starting ibex_csr Testbench ===");
    clk = 0;
    rst_n = 0;
    wr_data = '0;
    wr_en = 0;

    // Reset
    #10;
    rst_n = 1;
    #10;

    // Check reset value
    if (rd_data !== RESET_VALUE)
      $error("Reset value mismatch: expected %h, got %h", RESET_VALUE, rd_data);

    // Loop di test su 100 valori
    for (int i = 1; i < NUM_TESTS; i++) begin
      wr_data = i * 32'h01010101; // Valori pseudo-random
      wr_en = 1;
      #10;
      wr_en = 0;
      wr_data = 0;
      #5;
      rst_n = 0;
      #5;
      rst_n = 1;

      // Verifica lettura
      if (rd_data !== wr_data)
        $error("Mismatch at iteration %0d: expected %h, got %h", i, wr_data, rd_data);

      // Verifica integrità shadow
      if (rd_error)
        $error("Shadow copy error at iteration %0d", i);
    end

    $display("=== Testbench completed successfully ===");
    $finish;
  end

endmodule

DATE_tests/ibex_csr/ibex_csr.vcd
$date
	Thu Aug 21 16:36:16 2025
$end
$version
	ModelSim Version 2019.4
$end
$timescale
	1ns
$end

$scope module tb_ibex_csr $end
$var parameter 32 ! WIDTH $end
$var parameter 1 " SHADOW_COPY $end
$var parameter 32 # RESET_VALUE $end
$var parameter 32 $ NUM_TESTS $end
$var reg 1 % clk $end
$var reg 1 & rst_n $end
$var reg 32 ' wr_data [31:0] $end
$var reg 1 ( wr_en $end
$var reg 32 ) rd_data [31:0] $end
$var reg 1 * rd_error $end

$scope module dut $end
$var parameter 32 + Width $end
$var parameter 1 , ShadowCopy $end
$var parameter 32 - ResetValue $end
$var wire 1 . clk_i $end
$var wire 1 / rst_ni $end
$var wire 1 0 wr_data_i [31] $end
$var wire 1 1 wr_data_i [30] $end
$var wire 1 2 wr_data_i [29] $end
$var wire 1 3 wr_data_i [28] $end
$var wire 1 4 wr_data_i [27] $end
$var wire 1 5 wr_data_i [26] $end
$var wire 1 6 wr_data_i [25] $end
$var wire 1 7 wr_data_i [24] $end
$var wire 1 8 wr_data_i [23] $end
$var wire 1 9 wr_data_i [22] $end
$var wire 1 : wr_data_i [21] $end
$var wire 1 ; wr_data_i [20] $end
$var wire 1 < wr_data_i [19] $end
$var wire 1 = wr_data_i [18] $end
$var wire 1 > wr_data_i [17] $end
$var wire 1 ? wr_data_i [16] $end
$var wire 1 @ wr_data_i [15] $end
$var wire 1 A wr_data_i [14] $end
$var wire 1 B wr_data_i [13] $end
$var wire 1 C wr_data_i [12] $end
$var wire 1 D wr_data_i [11] $end
$var wire 1 E wr_data_i [10] $end
$var wire 1 F wr_data_i [9] $end
$var wire 1 G wr_data_i [8] $end
$var wire 1 H wr_data_i [7] $end
$var wire 1 I wr_data_i [6] $end
$var wire 1 J wr_data_i [5] $end
$var wire 1 K wr_data_i [4] $end
$var wire 1 L wr_data_i [3] $end
$var wire 1 M wr_data_i [2] $end
$var wire 1 N wr_data_i [1] $end
$var wire 1 O wr_data_i [0] $end
$var wire 1 P wr_en_i $end
$var reg 32 Q rd_data_o [31:0] $end
$var reg 1 R rd_error_o $end
$var reg 32 S rdata_q [31:0] $end

$scope begin gen_shadow $end
$var reg 32 T shadow_q [31:0] $end
$upscope $end
$upscope $end
$upscope $end
$enddefinitions $end
#0
$dumpvars
0%
0&
b0 '
0(
b0 )
0*
b0 Q
0R
b0 S
b11111111111111111111111111111111 T
b100000 !
b1 "
b0 #
b1100100 $
b100000 +
b1 ,
b0 -
0P
0O
0N
0M
0L
0K
0J
0I
0H
0G
0F
0E
0D
0C
0B
0A
0@
0?
0>
0=
0<
0;
0:
09
08
07
06
05
04
03
02
01
00
0/
0.
$end
#5
1%
1.
#10
1&
0%
1/
0.
#15
1%
1.
#20
b1000000010000000100000001 '
1(
0%
1O
1G
1?
17
1P
0.
#25
1%
1.
b1000000010000000100000001 S
b11111110111111101111111011111110 T
b1000000010000000100000001 Q
b1000000010000000100000001 )
#30
0(
b0 '
0%
0P
0O
0G
0?
07
0.
#35
0&
1%
0/
1.
b0 S
b11111111111111111111111111111111 T
b0 Q
b0 )
#40
1&
b10000000100000001000000010 '
1(
0%
1N
1F
1>
16
1P
1/
0.
#45
1%
1.
b10000000100000001000000010 S
b11111101111111011111110111111101 T
b10000000100000001000000010 Q
b10000000100000001000000010 )
#50
0(
b0 '
0%
0P
0N
0F
0>
06
0.
#55
0&
1%
0/
1.
b0 S
b11111111111111111111111111111111 T
b0 Q
b0 )
#60
1&
b11000000110000001100000011 '
1(
0%
1O
1N
1G
1F
1?
1>
17
16
1P
1/
0.
#65
1%
1.
b11000000110000001100000011 S
b11111100111111001111110011111100 T
b11000000110000001100000011 Q
b11000000110000001100000011 )
#70
0(
b0 '
0%
0P
0O
0N
0G
0F
0?
0>
07
06
0.
#75
0&
1%
0/
1.
b0 S
b11111111111111111111111111111111 T
b0 Q
b0 )
#80
1&
b100000001000000010000000100 '
1(
0%
1M
1E
1=
15
1P
1/
0.
#85
1%
1.
b100000001000000010000000100 S
b11111011111110111111101111111011 T
b100000001000000010000000100 Q
b100000001000000010000000100 )
#90
0(
b0 '
0%
0P
0M
0E
0=
05
0.
#95
0&
1%
0/
1.
b0 S
b11111111111111111111111111111111 T
b0 Q
b0 )
#100
1&
b101000001010000010100000101 '
1(
0%
1O
1M
1G
1E
1?
1=
17
15
1P
1/
0.
#105
1%
1.
b101000001010000010100000101 S
b11111010111110101111101011111010 T
b101000001010000010100000101 Q
b101000001010000010100000101 )
#110
0(
b0 '
0%
0P
0O
0M
0G
0E
0?
0=
07
05
0.
#115
0&
1%
0/
1.
b0 S
b11111111111111111111111111111111 T
b0 Q
b0 )
#120
1&
b110000001100000011000000110 '
1(
0%
1N
1M
1F
1E
1>
1=
16
15
1P
1/
0.
#125
1%
1.
b110000001100000011000000110 S
b11111001111110011111100111111001 T
b110000001100000011000000110 Q
b110000001100000011000000110 )
#130
0(
b0 '
0%
0P
0N
0M
0F
0E
0>
0=
06
05
0.
#135
0&
1%
0/
1.
b0 S
b11111111111111111111111111111111 T
b0 Q
b0 )
#140
1&
b111000001110000011100000111 '
1(
0%
1O
1N
1M
1G
1F
1E
1?
1>
1=
17
16
15
1P
1/
0.
#145
1%
1.
b111000001110000011100000111 S
b11111000111110001111100011111000 T
b111000001110000011100000111 Q
b111000001110000011100000111 )
#150
0(
b0 '
0%
0P
0O
0N
0M
0G
0F
0E
0?
0>
0=
07
06
05
0.
#155
0&
1%
0/
1.
b0 S
b11111111111111111111111111111111 T
b0 Q
b0 )
#160
1&
b1000000010000000100000001000 '
1(
0%
1L
1D
1<
14
1P
1/
0.
#165
1%
1.
b1000000010000000100000001000 S
b11110111111101111111011111110111 T
b1000000010000000100000001000 Q
b1000000010000000100000001000 )
#170
0(
b0 '
0%
0P
0L
0D
0<
04
0.
#175
0&
1%
0/
1.
b0 S
b11111111111111111111111111111111 T
b0 Q
b0 )
#180
1&
b1001000010010000100100001001 '
1(
0%
1O
1L
1G
1D
1?
1<
17
14
1P
1/
0.
#185
1%
1.
b1001000010010000100100001001 S
b11110110111101101111011011110110 T
b1001000010010000100100001001 Q
b1001000010010000100100001001 )
#190
0(
b0 '
0%
0P
0O
0L
0G
0D
0?
0<
07
04
0.
#195
0&
1%
0/
1.
b0 S
b11111111111111111111111111111111 T
b0 Q
b0 )
#200
1&
b1010000010100000101000001010 '
1(
0%
1N
1L
1F
1D
1>
1<
16
14
1P
1/
0.
#205
1%
1.
b1010000010100000101000001010 S
b11110101111101011111010111110101 T
b1010000010100000101000001010 Q
b1010000010100000101000001010 )
#210
0(
b0 '
0%
0P
0N
0L
0F
0D
0>
0<
06
04
0.
#215
0&
1%
0/
1.
b0 S
b11111111111111111111111111111111 T
b0 Q
b0 )
#220
1&
b1011000010110000101100001011 '
1(
0%
1O
1N
1L
1G
1F
1D
1?
1>
1<
17
16
14
1P
1/
0.
#225
1%
1.
b1011000010110000101100001011 S
b11110100111101001111010011110100 T
b1011000010110000101100001011 Q
b1011000010110000101100001011 )
#230
0(
b0 '
0%
0P
0O
0N
0L
0G
0F
0D
0?
0>
0<
07
06
04
0.
#235
0&
1%
0/
1.
b0 S
b11111111111111111111111111111111 T
b0 Q
b0 )
#240
1&
b1100000011000000110000001100 '
1(
0%
1M
1L
1E
1D
1=
1<
15
14
1P
1/
0.
#245
1%
1.
b1100000011000000110000001100 S
b11110011111100111111001111110011 T
b1100000011000000110000001100 Q
b1100000011000000110000001100 )
#250
0(
b0 '
0%
0P
0M
0L
0E
0D
0=
0<
05
04
0.
#255
0&
1%
0/
1.
b0 S
b11111111111111111111111111111111 T
b0 Q
b0 )
#260
1&
b1101000011010000110100001101 '
1(
0%
1O
1M
1L
1G
1E
1D
1?
1=
1<
17
15
14
1P
1/
0.
#265
1%
1.
b1101000011010000110100001101 S
b11110010111100101111001011110010 T
b1101000011010000110100001101 Q
b1101000011010000110100001101 )
#270
0(
b0 '
0%
0P
0O
0M
0L
0G
0E
0D
0?
0=
0<
07
05
04
0.
#275
0&
1%
0/
1.
b0 S
b11111111111111111111111111111111 T
b0 Q
b0 )
#280
1&
b1110000011100000111000001110 '
1(
0%
1N
1M
1L
1F
1E
1D
1>
1=
1<
16
15
14
1P
1/
0.
#285
1%
1.
b1110000011100000111000001110 S
b11110001111100011111000111110001 T
b1110000011100000111000001110 Q
b1110000011100000111000001110 )
#290
0(
b0 '
0%
0P
0N
0M
0L
0F
0E
0D
0>
0=
0<
06
05
04
0.
#295
0&
1%
0/
1.
b0 S
b11111111111111111111111111111111 T
b0 Q
b0 )
#300
1&
b1111000011110000111100001111 '
1(
0%
1O
1N
1M
1L
1G
1F
1E
1D
1?
1>
1=
1<
17
16
15
14
1P
1/
0.
#305
1%
1.
b1111000011110000111100001111 S
b11110000111100001111000011110000 T
b1111000011110000111100001111 Q
b1111000011110000111100001111 )
#310
0(
b0 '
0%
0P
0O
0N
0M
0L
0G
0F
0E
0D
0?
0>
0=
0<
07
06
05
04
0.
#315
0&
1%
0/
1.
b0 S
b11111111111111111111111111111111 T
b0 Q
b0 )
#320
1&
b10000000100000001000000010000 '
1(
0%
1K
1C
1;
13
1P
1/
0.
#325
1%
1.
b10000000100000001000000010000 S
b11101111111011111110111111101111 T
b10000000100000001000000010000 Q
b10000000100000001000000010000 )
#330
0(
b0 '
0%
0P
0K
0C
0;
03
0.
#335
0&
1%
0/
1.
b0 S
b11111111111111111111111111111111 T
b0 Q
b0 )
#340
1&
b10001000100010001000100010001 '
1(
0%
1O
1K
1G
1C
1?
1;
17
13
1P
1/
0.
#345
1%
1.
b10001000100010001000100010001 S
b11101110111011101110111011101110 T
b10001000100010001000100010001 Q
b10001000100010001000100010001 )
#350
0(
b0 '
0%
0P
0O
0K
0G
0C
0?
0;
07
03
0.
#355
0&
1%
0/
1.
b0 S
b11111111111111111111111111111111 T
b0 Q
b0 )
#360
1&
b10010000100100001001000010010 '
1(
0%
1N
1K
1F
1C
1>
1;
16
13
1P
1/
0.
#365
1%
1.
b10010000100100001001000010010 S
b11101101111011011110110111101101 T
b10010000100100001001000010010 Q
b10010000100100001001000010010 )
#370
0(
b0 '
0%
0P
0N
0K
0F
0C
0>
0;
06
03
0.
#375
0&
1%
0/
1.
b0 S
b11111111111111111111111111111111 T
b0 Q
b0 )
#380
1&
b10011000100110001001100010011 '
1(
0%
1O
1N
1K
1G
1F
1C
1?
1>
1;
17
16
13
1P
1/
0.
#385
1%
1.
b10011000100110001001100010011 S
b11101100111011001110110011101100 T
b10011000100110001001100010011 Q
b10011000100110001001100010011 )
#390
0(
b0 '
0%
0P
0O
0N
0K
0G
0F
0C
0?
0>
0;
07
06
03
0.
#395
0&
1%
0/
1.
b0 S
b11111111111111111111111111111111 T
b0 Q
b0 )
#400
1&
b10100000101000001010000010100 '
1(
0%
1M
1K
1E
1C
1=
1;
15
13
1P
1/
0.
#405
1%
1.
b10100000101000001010000010100 S
b11101011111010111110101111101011 T
b10100000101000001010000010100 Q
b10100000101000001010000010100 )
#410
0(
b0 '
0%
0P
0M
0K
0E
0C
0=
0;
05
03
0.
#415
0&
1%
0/
1.
b0 S
b11111111111111111111111111111111 T
b0 Q
b0 )
#420
1&
b10101000101010001010100010101 '
1(
0%
1O
1M
1K
1G
1E
1C
1?
1=
1;
17
15
13
1P
1/
0.
#425
1%
1.
b10101000101010001010100010101 S
b11101010111010101110101011101010 T
b10101000101010001010100010101 Q
b10101000101010001010100010101 )
#430
0(
b0 '
0%
0P
0O
0M
0K
0G
0E
0C
0?
0=
0;
07
05
03
0.
#435
0&
1%
0/
1.
b0 S
b11111111111111111111111111111111 T
b0 Q
b0 )
#440
1&
b10110000101100001011000010110 '
1(
0%
1N
1M
1K
1F
1E
1C
1>
1=
1;
16
15
13
1P
1/
0.
#445
1%
1.
b10110000101100001011000010110 S
b11101001111010011110100111101001 T
b10110000101100001011000010110 Q
b10110000101100001011000010110 )
#450
0(
b0 '
0%
0P
0N
0M
0K
0F
0E
0C
0>
0=
0;
06
05
03
0.
#455
0&
1%
0/
1.
b0 S
b11111111111111111111111111111111 T
b0 Q
b0 )
#460
1&
b10111000101110001011100010111 '
1(
0%
1O
1N
1M
1K
1G
1F
1E
1C
1?
1>
1=
1;
17
16
15
13
1P
1/
0.
#465
1%
1.
b10111000101110001011100010111 S
b11101000111010001110100011101000 T
b10111000101110001011100010111 Q
b10111000101110001011100010111 )
#470
0(
b0 '
0%
0P
0O
0N
0M
0K
0G
0F
0E
0C
0?
0>
0=
0;
07
06
05
03
0.
#475
0&
1%
0/
1.
b0 S
b11111111111111111111111111111111 T
b0 Q
b0 )
#480
1&
b11000000110000001100000011000 '
1(
0%
1L
1K
1D
1C
1<
1;
14
13
1P
1/
0.
#485
1%
1.
b11000000110000001100000011000 S
b11100111111001111110011111100111 T
b11000000110000001100000011000 Q
b11000000110000001100000011000 )
#490
0(
b0 '
0%
0P
0L
0K
0D
0C
0<
0;
04
03
0.
#495
0&
1%
0/
1.
b0 S
b11111111111111111111111111111111 T
b0 Q
b0 )
#500
1&
b11001000110010001100100011001 '
1(
0%
1O
1L
1K
1G
1D
1C
1?
1<
1;
17
14
13
1P
1/
0.
#505
1%
1.
b11001000110010001100100011001 S
b11100110111001101110011011100110 T
b11001000110010001100100011001 Q
b11001000110010001100100011001 )
#510
0(
b0 '
0%
0P
0O
0L
0K
0G
0D
0C
0?
0<
0;
07
04
03
0.
#515
0&
1%
0/
1.
b0 S
b11111111111111111111111111111111 T
b0 Q
b0 )
#520
1&
b11010000110100001101000011010 '
1(
0%
1N
1L
1K
1F
1D
1C
1>
1<
1;
16
14
13
1P
1/
0.
#525
1%
1.
b11010000110100001101000011010 S
b11100101111001011110010111100101 T
b11010000110100001101000011010 Q
b11010000110100001101000011010 )
#530
0(
b0 '
0%
0P
0N
0L
0K
0F
0D
0C
0>
0<
0;
06
04
03
0.
#535
0&
1%
0/
1.
b0 S
b11111111111111111111111111111111 T
b0 Q
b0 )
#540
1&
b11011000110110001101100011011 '
1(
0%
1O
1N
1L
1K
1G
1F
1D
1C
1?
1>
1<
1;
17
16
14
13
1P
1/
0.
#545
1%
1.
b11011000110110001101100011011 S
b11100100111001001110010011100100 T
b11011000110110001101100011011 Q
b11011000110110001101100011011 )
#550
0(
b0 '
0%
0P
0O
0N
0L
0K
0G
0F
0D
0C
0?
0>
0<
0;
07
06
04
03
0.
#555
0&
1%
0/
1.
b0 S
b11111111111111111111111111111111 T
b0 Q
b0 )
#560
1&
b11100000111000001110000011100 '
1(
0%
1M
1L
1K
1E
1D
1C
1=
1<
1;
15
14
13
1P
1/
0.
#565
1%
1.
b11100000111000001110000011100 S
b11100011111000111110001111100011 T
b11100000111000001110000011100 Q
b11100000111000001110000011100 )
#570
0(
b0 '
0%
0P
0M
0L
0K
0E
0D
0C
0=
0<
0;
05
04
03
0.
#575
0&
1%
0/
1.
b0 S
b11111111111111111111111111111111 T
b0 Q
b0 )
#580
1&
b11101000111010001110100011101 '
1(
0%
1O
1M
1L
1K
1G
1E
1D
1C
1?
1=
1<
1;
17
15
14
13
1P
1/
0.
#585
1%
1.
b11101000111010001110100011101 S
b11100010111000101110001011100010 T
b11101000111010001110100011101 Q
b11101000111010001110100011101 )
#590
0(
b0 '
0%
0P
0O
0M
0L
0K
0G
0E
0D
0C
0?
0=
0<
0;
07
05
04
03
0.
#595
0&
1%
0/
1.
b0 S
b11111111111111111111111111111111 T
b0 Q
b0 )
#600
1&
b11110000111100001111000011110 '
1(
0%
1N
1M
1L
1K
1F
1E
1D
1C
1>
1=
1<
1;
16
15
14
13
1P
1/
0.
#605
1%
1.
b11110000111100001111000011110 S
b11100001111000011110000111100001 T
b11110000111100001111000011110 Q
b11110000111100001111000011110 )
#610
0(
b0 '
0%
0P
0N
0M
0L
0K
0F
0E
0D
0C
0>
0=
0<
0;
06
05
04
03
0.
#615
0&
1%
0/
1.
b0 S
b11111111111111111111111111111111 T
b0 Q
b0 )
#620
1&
b11111000111110001111100011111 '
1(
0%
1O
1N
1M
1L
1K
1G
1F
1E
1D
1C
1?
1>
1=
1<
1;
17
16
15
14
13
1P
1/
0.
#625
1%
1.
b11111000111110001111100011111 S
b11100000111000001110000011100000 T
b11111000111110001111100011111 Q
b11111000111110001111100011111 )
#630
0(
b0 '
0%
0P
0O
0N
0M
0L
0K
0G
0F
0E
0D
0C
0?
0>
0=
0<
0;
07
06
05
04
03
0.
#635
0&
1%
0/
1.
b0 S
b11111111111111111111111111111111 T
b0 Q
b0 )
#640
1&
b100000001000000010000000100000 '
1(
0%
1J
1B
1:
12
1P
1/
0.
#645
1%
1.
b100000001000000010000000100000 S
b11011111110111111101111111011111 T
b100000001000000010000000100000 Q
b100000001000000010000000100000 )
#650
0(
b0 '
0%
0P
0J
0B
0:
02
0.
#655
0&
1%
0/
1.
b0 S
b11111111111111111111111111111111 T
b0 Q
b0 )
#660
1&
b100001001000010010000100100001 '
1(
0%
1O
1J
1G
1B
1?
1:
17
12
1P
1/
0.
#665
1%
1.
b100001001000010010000100100001 S
b11011110110111101101111011011110 T
b100001001000010010000100100001 Q
b100001001000010010000100100001 )
#670
0(
b0 '
0%
0P
0O
0J
0G
0B
0?
0:
07
02
0.
#675
0&
1%
0/
1.
b0 S
b11111111111111111111111111111111 T
b0 Q
b0 )
#680
1&
b100010001000100010001000100010 '
1(
0%
1N
1J
1F
1B
1>
1:
16
12
1P
1/
0.
#685
1%
1.
b100010001000100010001000100010 S
b11011101110111011101110111011101 T
b100010001000100010001000100010 Q
b100010001000100010001000100010 )
#690
0(
b0 '
0%
0P
0N
0J
0F
0B
0>
0:
06
02
0.
#695
0&
1%
0/
1.
b0 S
b11111111111111111111111111111111 T
b0 Q
b0 )
#700
1&
b100011001000110010001100100011 '
1(
0%
1O
1N
1J
1G
1F
1B
1?
1>
1:
17
16
12
1P
1/
0.
#705
1%
1.
b100011001000110010001100100011 S
b11011100110111001101110011011100 T
b100011001000110010001100100011 Q
b100011001000110010001100100011 )
#710
0(
b0 '
0%
0P
0O
0N
0J
0G
0F
0B
0?
0>
0:
07
06
02
0.
#715
0&
1%
0/
1.
b0 S
b11111111111111111111111111111111 T
b0 Q
b0 )
#720
1&
b100100001001000010010000100100 '
1(
0%
1M
1J
1E
1B
1=
1:
15
12
1P
1/
0.
#725
1%
1.
b100100001001000010010000100100 S
b11011011110110111101101111011011 T
b100100001001000010010000100100 Q
b100100001001000010010000100100 )
#730
0(
b0 '
0%
0P
0M
0J
0E
0B
0=
0:
05
02
0.
#735
0&
1%
0/
1.
b0 S
b11111111111111111111111111111111 T
b0 Q
b0 )
#740
1&
b100101001001010010010100100101 '
1(
0%
1O
1M
1J
1G
1E
1B
1?
1=
1:
17
15
12
1P
1/
0.
#745
1%
1.
b100101001001010010010100100101 S
b11011010110110101101101011011010 T
b100101001001010010010100100101 Q
b100101001001010010010100100101 )
#750
0(
b0 '
0%
0P
0O
0M
0J
0G
0E
0B
0?
0=
0:
07
05
02
0.
#755
0&
1%
0/
1.
b0 S
b11111111111111111111111111111111 T
b0 Q
b0 )
#760
1&
b100110001001100010011000100110 '
1(
0%
1N
1M
1J
1F
1E
1B
1>
1=
1:
16
15
12
1P
1/
0.
#765
1%
1.
b100110001001100010011000100110 S
b11011001110110011101100111011001 T
b100110001001100010011000100110 Q
b100110001001100010011000100110 )
#770
0(
b0 '
0%
0P
0N
0M
0J
0F
0E
0B
0>
0=
0:
06
05
02
0.
#775
0&
1%
0/
1.
b0 S
b11111111111111111111111111111111 T
b0 Q
b0 )
#780
1&
b100111001001110010011100100111 '
1(
0%
1O
1N
1M
1J
1G
1F
1E
1B
1?
1>
1=
1:
17
16
15
12
1P
1/
0.
#785
1%
1.
b100111001001110010011100100111 S
b11011000110110001101100011011000 T
b100111001001110010011100100111 Q
b100111001001110010011100100111 )
#790
0(
b0 '
0%
0P
0O
0N
0M
0J
0G
0F
0E
0B
0?
0>
0=
0:
07
06
05
02
0.
#795
0&
1%
0/
1.
b0 S
b11111111111111111111111111111111 T
b0 Q
b0 )
#800
1&
b101000001010000010100000101000 '
1(
0%
1L
1J
1D
1B
1<
1:
14
12
1P
1/
0.
#805
1%
1.
b101000001010000010100000101000 S
b11010111110101111101011111010111 T
b101000001010000010100000101000 Q
b101000001010000010100000101000 )
#810
0(
b0 '
0%
0P
0L
0J
0D
0B
0<
0:
04
02
0.
#815
0&
1%
0/
1.
b0 S
b11111111111111111111111111111111 T
b0 Q
b0 )
#820
1&
b101001001010010010100100101001 '
1(
0%
1O
1L
1J
1G
1D
1B
1?
1<
1:
17
14
12
1P
1/
0.
#825
1%
1.
b101001001010010010100100101001 S
b11010110110101101101011011010110 T
b101001001010010010100100101001 Q
b101001001010010010100100101001 )
#830
0(
b0 '
0%
0P
0O
0L
0J
0G
0D
0B
0?
0<
0:
07
04
02
0.
#835
0&
1%
0/
1.
b0 S
b11111111111111111111111111111111 T
b0 Q
b0 )
#840
1&
b101010001010100010101000101010 '
1(
0%
1N
1L
1J
1F
1D
1B
1>
1<
1:
16
14
12
1P
1/
0.
#845
1%
1.
b101010001010100010101000101010 S
b11010101110101011101010111010101 T
b101010001010100010101000101010 Q
b101010001010100010101000101010 )
#850
0(
b0 '
0%
0P
0N
0L
0J
0F
0D
0B
0>
0<
0:
06
04
02
0.
#855
0&
1%
0/
1.
b0 S
b11111111111111111111111111111111 T
b0 Q
b0 )
#860
1&
b101011001010110010101100101011 '
1(
0%
1O
1N
1L
1J
1G
1F
1D
1B
1?
1>
1<
1:
17
16
14
12
1P
1/
0.
#865
1%
1.
b101011001010110010101100101011 S
b11010100110101001101010011010100 T
b101011001010110010101100101011 Q
b101011001010110010101100101011 )
#870
0(
b0 '
0%
0P
0O
0N
0L
0J
0G
0F
0D
0B
0?
0>
0<
0:
07
06
04
02
0.
#875
0&
1%
0/
1.
b0 S
b11111111111111111111111111111111 T
b0 Q
b0 )
#880
1&
b101100001011000010110000101100 '
1(
0%
1M
1L
1J
1E
1D
1B
1=
1<
1:
15
14
12
1P
1/
0.
#885
1%
1.
b101100001011000010110000101100 S
b11010011110100111101001111010011 T
b101100001011000010110000101100 Q
b101100001011000010110000101100 )
#890
0(
b0 '
0%
0P
0M
0L
0J
0E
0D
0B
0=
0<
0:
05
04
02
0.
#895
0&
1%
0/
1.
b0 S
b11111111111111111111111111111111 T
b0 Q
b0 )
#900
1&
b101101001011010010110100101101 '
1(
0%
1O
1M
1L
1J
1G
1E
1D
1B
1?
1=
1<
1:
17
15
14
12
1P
1/
0.
#905
1%
1.
b101101001011010010110100101101 S
b11010010110100101101001011010010 T
b101101001011010010110100101101 Q
b101101001011010010110100101101 )
#910
0(
b0 '
0%
0P
0O
0M
0L
0J
0G
0E
0D
0B
0?
0=
0<
0:
07
05
04
02
0.
#915
0&
1%
0/
1.
b0 S
b11111111111111111111111111111111 T
b0 Q
b0 )
#920
1&
b101110001011100010111000101110 '
1(
0%
1N
1M
1L
1J
1F
1E
1D
1B
1>
1=
1<
1:
16
15
14
12
1P
1/
0.
#925
1%
1.
b101110001011100010111000101110 S
b11010001110100011101000111010001 T
b101110001011100010111000101110 Q
b101110001011100010111000101110 )
#930
0(
b0 '
0%
0P
0N
0M
0L
0J
0F
0E
0D
0B
0>
0=
0<
0:
06
05
04
02
0.
#935
0&
1%
0/
1.
b0 S
b11111111111111111111111111111111 T
b0 Q
b0 )
#940
1&
b101111001011110010111100101111 '
1(
0%
1O
1N
1M
1L
1J
1G
1F
1E
1D
1B
1?
1>
1=
1<
1:
17
16
15
14
12
1P
1/
0.
#945
1%
1.
b101111001011110010111100101111 S
b11010000110100001101000011010000 T
b101111001011110010111100101111 Q
b101111001011110010111100101111 )
#950
0(
b0 '
0%
0P
0O
0N
0M
0L
0J
0G
0F
0E
0D
0B
0?
0>
0=
0<
0:
07
06
05
04
02
0.
#955
0&
1%
0/
1.
b0 S
b11111111111111111111111111111111 T
b0 Q
b0 )
#960
1&
b110000001100000011000000110000 '
1(
0%
1K
1J
1C
1B
1;
1:
13
12
1P
1/
0.
#965
1%
1.
b110000001100000011000000110000 S
b11001111110011111100111111001111 T
b110000001100000011000000110000 Q
b110000001100000011000000110000 )
#970
0(
b0 '
0%
0P
0K
0J
0C
0B
0;
0:
03
02
0.
#975
0&
1%
0/
1.
b0 S
b11111111111111111111111111111111 T
b0 Q
b0 )
#980
1&
b110001001100010011000100110001 '
1(
0%
1O
1K
1J
1G
1C
1B
1?
1;
1:
17
13
12
1P
1/
0.
#985
1%
1.
b110001001100010011000100110001 S
b11001110110011101100111011001110 T
b110001001100010011000100110001 Q
b110001001100010011000100110001 )
#990
0(
b0 '
0%
0P
0O
0K
0J
0G
0C
0B
0?
0;
0:
07
03
02
0.
#995
0&
1%
0/
1.
b0 S
b11111111111111111111111111111111 T
b0 Q
b0 )
#1000
1&
b110010001100100011001000110010 '
1(
0%
1N
1K
1J
1F
1C
1B
1>
1;
1:
16
13
12
1P
1/
0.
#1005
1%
1.
b110010001100100011001000110010 S
b11001101110011011100110111001101 T
b110010001100100011001000110010 Q
b110010001100100011001000110010 )
#1010
0(
b0 '
0%
0P
0N
0K
0J
0F
0C
0B
0>
0;
0:
06
03
02
0.
#1015
0&
1%
0/
1.
b0 S
b11111111111111111111111111111111 T
b0 Q
b0 )
#1020
1&
b110011001100110011001100110011 '
1(
0%
1O
1N
1K
1J
1G
1F
1C
1B
1?
1>
1;
1:
17
16
13
12
1P
1/
0.
#1025
1%
1.
b110011001100110011001100110011 S
b11001100110011001100110011001100 T
b110011001100110011001100110011 Q
b110011001100110011001100110011 )
#1030
0(
b0 '
0%
0P
0O
0N
0K
0J
0G
0F
0C
0B
0?
0>
0;
0:
07
06
03
02
0.
#1035
0&
1%
0/
1.
b0 S
b11111111111111111111111111111111 T
b0 Q
b0 )
#1040
1&
b110100001101000011010000110100 '
1(
0%
1M
1K
1J
1E
1C
1B
1=
1;
1:
15
13
12
1P
1/
0.
#1045
1%
1.
b110100001101000011010000110100 S
b11001011110010111100101111001011 T
b110100001101000011010000110100 Q
b110100001101000011010000110100 )
#1050
0(
b0 '
0%
0P
0M
0K
0J
0E
0C
0B
0=
0;
0:
05
03
02
0.
#1055
0&
1%
0/
1.
b0 S
b11111111111111111111111111111111 T
b0 Q
b0 )
#1060
1&
b110101001101010011010100110101 '
1(
0%
1O
1M
1K
1J
1G
1E
1C
1B
1?
1=
1;
1:
17
15
13
12
1P
1/
0.
#1065
1%
1.
b110101001101010011010100110101 S
b11001010110010101100101011001010 T
b110101001101010011010100110101 Q
b110101001101010011010100110101 )
