Designs_old/sqrt/old/old_rtl/sqrt_calculator_old.v
module sqrt_calculator (
    input wire clk,
    input wire rst,
    input wire start,
    input wire [15:0] in,
    output reg [7:0] out,
    output reg error,
    output reg done
);

    reg [15:0] num;
    reg [7:0] guess;
    reg [3:0] iter;

    always @(posedge clk or posedge rst) begin
        if (rst) begin
            out <= 0;
            error <= 0;
            done <= 0;
            num <= 0;
            guess <= 0;
            iter <= 0;
        end else if (start) begin
            if (in[15] == 1) begin // Check if input is negative: Assuming 2's complement for input
                error <= 1;
                done <= 1;
            end else begin
                num <= in;
                guess <= 8'd1; // Initial guess
                iter <= 0;
                error <= 0;
                done <= 0;
            end
        end else if (!done) begin
            if (iter < 10) begin
                guess <= (guess + (num / guess)) >> 1; // Newton-Raphson method
                iter <= iter + 1;
            end else begin
                out <= guess;
                done <= 1;
            end
        end
    end

endmodule

Designs/sqrt/tb/tb.v
module sqrt_calculator_tb;
    reg clk;
    reg rst;
    reg start;
    reg [15:0] in;
    wire [7:0] out;
    wire error;
    wire done;

    sqrt_calculator uut (
        .clk(clk),
        .rst(rst),
        .start(start),
        .in(in),
        .out(out),
        .error(error),
        .done(done)
    );

    always #5 clk = ~clk; // Clock with 10 time unit period

    initial begin
        $dumpfile("sqrt_calculator_tb.vcd");
        $dumpvars(0, sqrt_calculator_tb);
        
        clk = 0;
        rst = 1;
        start = 0;
        in = 0;
        
        #10 rst = 0;

        // Test case 1: Valid input (16), expected output 4
        #10 in = 16; start = 1;
        #10 start = 0;
        wait(done);
        $display("Input: %d, Output: %d, Error: %b", in, out, error);
        
        // Test case 2: Valid input (25), expected output 5
        #10 in = 25; start = 1;
        #10 start = 0;
        wait(done);
        $display("Input: %d, Output: %d, Error: %b", in, out, error);
        
        // Test case 3: Negative input (-1), expected error flag
        #10 in = -1; start = 1;
        #10 start = 0;
        wait(done);
        $display("Input: %d, Output: %d, Error: %b", in, out, error);

        // Test case 4: Zero input, expected output 0
        #10 in = 0; start = 1;
        #10 start = 0;
        wait(done);
        $display("Input: %d, Output: %d, Error: %b", in, out, error);
        
        #20 $finish;
    end
endmodule

DATE_tests/sqrt/sqrt_simple_tb.vcd
$date
	Sun Jul  6 10:53:16 2025
$end
$version
	ModelSim Version 2019.4
$end
$timescale
	1ns
$end

$scope module sqrt_calculator_tb $end
$var reg 1 ! clk $end
$var reg 1 " rst $end
$var reg 1 # start $end
$var reg 16 $ in [15:0] $end
$var wire 1 % out [7] $end
$var wire 1 & out [6] $end
$var wire 1 ' out [5] $end
$var wire 1 ( out [4] $end
$var wire 1 ) out [3] $end
$var wire 1 * out [2] $end
$var wire 1 + out [1] $end
$var wire 1 , out [0] $end
$var wire 1 - error $end
$var wire 1 . done $end

$scope module uut $end
$var wire 1 / clk $end
$var wire 1 0 rst $end
$var wire 1 1 start $end
$var wire 1 2 in [15] $end
$var wire 1 3 in [14] $end
$var wire 1 4 in [13] $end
$var wire 1 5 in [12] $end
$var wire 1 6 in [11] $end
$var wire 1 7 in [10] $end
$var wire 1 8 in [9] $end
$var wire 1 9 in [8] $end
$var wire 1 : in [7] $end
$var wire 1 ; in [6] $end
$var wire 1 < in [5] $end
$var wire 1 = in [4] $end
$var wire 1 > in [3] $end
$var wire 1 ? in [2] $end
$var wire 1 @ in [1] $end
$var wire 1 A in [0] $end
$var reg 8 B out [7:0] $end
$var reg 1 C error $end
$var reg 1 D done $end
$var reg 16 E num [15:0] $end
$var reg 8 F guess [7:0] $end
$var reg 4 G iter [3:0] $end
$upscope $end
$upscope $end
$enddefinitions $end
#0
$dumpvars
0!
1"
0#
b0 $
b0 B
0C
0D
b0 E
b0 F
b0 G
0,
0+
0*
0)
0(
0'
0&
0%
0-
0.
0A
0@
0?
0>
0=
0<
0;
0:
09
08
07
06
05
04
03
02
01
10
0/
$end
#5
1!
1/
#10
0"
0!
00
0/
#15
1!
1/
bx F
b1 G
#20
b10000 $
1#
0!
1=
11
0/
#25
1!
1/
b10000 E
b1 F
b0 G
#30
0#
0!
01
0/
#35
1!
1/
b1000 F
b1 G
#40
0!
0/
#45
1!
1/
b101 F
b10 G
#50
0!
0/
#55
1!
1/
b100 F
b11 G
#60
0!
0/
#65
1!
1/
b100 G
#70
0!
0/
#75
1!
1/
b101 G
#80
0!
0/
#85
1!
1/
b110 G
#90
0!
0/
#95
1!
1/
b111 G
#100
0!
0/
#105
1!
1/
b1000 G
#110
0!
0/
#115
1!
1/
b1001 G
#120
0!
0/
#125
1!
1/
b1010 G
#130
0!
0/
#135
1!
1/
b100 B
1D
1*
1.
#140
0!
0/
#145
b11001 $
1#
1!
1A
1>
11
1/
b11001 E
b1 F
b0 G
0D
0.
#150
0!
0/
#155
0#
1!
01
1/
b1101 F
b1 G
#160
0!
0/
#165
1!
1/
b111 F
b10 G
#170
0!
0/
#175
1!
1/
b101 F
b11 G
#180
0!
0/
#185
1!
1/
b100 G
#190
0!
0/
#195
1!
1/
b101 G
#200
0!
0/
#205
1!
1/
b110 G
#210
0!
0/
#215
1!
1/
b111 G
#220
0!
0/
#225
1!
1/
b1000 G
#230
0!
0/
#235
1!
1/
b1001 G
#240
0!
0/
#245
1!
1/
b1010 G
#250
0!
0/
#255
1!
1/
b101 B
1D
1,
1.
#260
0!
0/
#265
b1111111111110110 $
1#
1!
0A
1@
1?
0>
1<
1;
1:
19
18
17
16
15
14
13
12
11
1/
1C
1-
#270
0!
0/
#275
0#
1!
01
1/
#280
0!
0/
#285
b0 $
1#
1!
0@
0?
0=
0<
0;
0:
09
08
07
06
05
04
03
02
11
1/
b0 E
b1 F
b0 G
0C
0D
0-
0.
#290
0!
0/
#295
0#
1!
01
1/
b0 F
b1 G
#300
0!
0/
#305
1!
1/
bx F
b10 G
#310
0!
0/
#315
1!
1/
b11 G
#320
0!
0/
#325
1!
1/
b100 G
#330
0!
0/
#335
1!
1/
b101 G
#340
0!
0/
#345
1!
1/
b110 G
#350
0!
0/
#355
1!
1/
b111 G
#360
0!
0/
#365
1!
1/
b1000 G
#370
0!
0/
#375
1!
1/
b1001 G
#380
0!
0/
#385
1!
1/
b1010 G
#390
0!
0/
#395
1!
1/
bx B
1D
x,
x+
x*
x)
x(
x'
x&
x%
1.
#400
0!
0/
#405
b10010 $
1#
1!
1@
1=
11
1/
b10010 E
b1 F
b0 G
0D
0.
#410
0!
0/
#415
0#
1!
01
1/
b1001 F
b1 G
#420
0!
0/
#425
1!
1/
b101 F
b10 G
#430
0!
0/
#435
1!
1/
b100 F
b11 G
#440
0!
0/
#445
1!
1/
b100 G
#450
0!
0/
#455
1!
1/
b101 G
#460
0!
0/
#465
1!
1/
b110 G
#470
0!
0/
#475
1!
1/
b111 G
#480
0!
0/
#485
1!
1/
b1000 G
#490
0!
0/
#495
1!
1/
b1001 G
#500
0!
0/
#505
1!
1/
b1010 G
#510
0!
0/
#515
1!
1/
b100 B
1D
0,
0+
1*
0)
0(
0'
0&
0%
1.
