Verilated-tests/accumulator/rtl/verified_accu.sv

module verified_accu(input clk, rst_n, input [7:0] data_in, input valid_in, output reg valid_out, output reg [9:0] data_out);
    
   reg [1:0] count;
   wire add_cnt;
   wire ready_add;
   wire end_cnt;
   reg [9:0]   data_out_reg;

   assign add_cnt = ready_add;
   assign end_cnt = ready_add && (count == 'd3);
   
   //count
   always @(posedge clk or negedge rst_n) begin
       if(!rst_n) begin
          count <= 0;
       end
       else if(end_cnt) begin
          count <= 0;
       end
       else if(add_cnt) begin
          count <= count + 1;
       end
   end

    //data_out_reg
   always @(posedge clk or negedge rst_n) begin
      if(!rst_n) begin
        data_out_reg <= 0;
      end
      else if (add_cnt && count == 0) begin
          data_out_reg <= data_in;
      end
      else if (add_cnt) begin
          data_out_reg <= data_out_reg + data_in;
      end
   end

    //data_out
   always @(posedge clk or negedge rst_n) begin
      if(!rst_n) begin
        data_out <= 0;
      end
      else if (add_cnt && count == 0) begin
          data_out <= data_in;
      end
      else if (add_cnt) begin
          data_out <= data_out + data_in;
      end
   end

   //ready_add
   assign ready_add = !valid_out | valid_in;

   //valid_out
   always @(posedge clk or negedge rst_n) begin
       if(!rst_n) begin
           valid_out <= 0;
       end
       else if(end_cnt) begin
           valid_out <= 1;
       end
       else begin
           valid_out <= 0;
       end
   end  
     
endmodule

legacy/fdl26/FDL26/FDL26_tests/accumulator/old/testbench.v
`timescale  1ns / 1ps

module tb_valid_ready;


parameter PERIOD  = 10;
reg   clk                                  = 0 ;
reg   rst_n                                = 0 ;
reg   [7:0]  data_in                       = 0 ;
reg   valid_in                             = 0 ;

wire  valid_out                              ;
wire  [9:0]  data_out                       ;


initial
begin
    forever #(PERIOD/2)  clk=~clk;
end

initial
begin
    #(PERIOD*2) rst_n  =  1;
end

verified_accu  uut (
    .clk                     ( clk             ),
    .rst_n                   ( rst_n           ),
    .data_in                 ( data_in   [7:0] ),
    .valid_in                ( valid_in        ),

    .valid_out               ( valid_out       ),
    .data_out                ( data_out  [9:0] )
);

initial
begin
    #(PERIOD*1+0.01); 
    #(PERIOD)   data_in = 8'd1;valid_in = 1;
    #(PERIOD)   data_in = 8'd2;
    #(PERIOD)   data_in = 8'd3;
    #(PERIOD)   data_in = 8'd14;

    #(PERIOD)   data_in = 8'd5;
    #(PERIOD)   data_in = 8'd2;
    #(PERIOD)   data_in = 8'd103;
    #(PERIOD)   data_in = 8'd4;

    #(PERIOD)   data_in = 8'd5;
    #(PERIOD)   data_in = 8'd6;
    #(PERIOD)   data_in = 8'd3;
    #(PERIOD)   data_in = 8'd54;
    #(PERIOD*2);
    $finish;
end

reg [9:0] result [0:2];
initial begin
    result[0] = 9'd20;
    result[1] = 9'd114;
    result[2] = 9'd68;
end

integer i;
integer casenum = 0;
integer error = 0;

initial
begin
    $dumpfile("accu.vcd");
    $dumpvars(0, tb_valid_ready);
    for (i = 0; i < 15; i = i + 1) begin
        #((PERIOD) * 1);         
        if (valid_out) begin
            error = (data_out == result[casenum]) ? error : error + 1;
            casenum = casenum + 1;
        end        
    end
    if(error==0 && casenum==3)
	begin
		$display("===========Your Design Passed===========");
        end
	else
	begin
		$display("===========Error===========");
	end
    $finish;
end


endmodule

DATE_tests/accumulator/old/accu.vcd
$date
	Wed Jul 23 16:35:55 2025
$end
$version
	ModelSim Version 2019.4
$end
$timescale
	1ps
$end

$scope module tb_valid_ready $end
$var parameter 32 ! PERIOD $end
$var reg 1 " clk $end
$var reg 1 # rst_n $end
$var reg 8 $ data_in [7:0] $end
$var reg 1 % valid_in $end
$var wire 1 & valid_out $end
$var wire 1 ' data_out [9] $end
$var wire 1 ( data_out [8] $end
$var wire 1 ) data_out [7] $end
$var wire 1 * data_out [6] $end
$var wire 1 + data_out [5] $end
$var wire 1 , data_out [4] $end
$var wire 1 - data_out [3] $end
$var wire 1 . data_out [2] $end
$var wire 1 / data_out [1] $end
$var wire 1 0 data_out [0] $end
$var integer 32 1 i $end
$var integer 32 2 casenum $end
$var integer 32 3 error $end

$scope module uut $end
$var wire 1 4 clk $end
$var wire 1 5 rst_n $end
$var wire 1 6 data_in [7] $end
$var wire 1 7 data_in [6] $end
$var wire 1 8 data_in [5] $end
$var wire 1 9 data_in [4] $end
$var wire 1 : data_in [3] $end
$var wire 1 ; data_in [2] $end
$var wire 1 < data_in [1] $end
$var wire 1 = data_in [0] $end
$var wire 1 > valid_in $end
$var reg 1 ? valid_out $end
$var reg 10 @ data_out [9:0] $end
$var reg 2 A count [1:0] $end
$var wire 1 B add_cnt $end
$var wire 1 C ready_add $end
$var wire 1 D end_cnt $end
$var reg 10 E data_out_reg [9:0] $end
$upscope $end
$upscope $end
$enddefinitions $end
#0
$dumpvars
0"
0#
b0 $
0%
0?
b0 @
b0 A
b0 E
b1010 !
b0 1
b0 2
b0 3
0&
00
0/
0.
0-
0,
0+
0*
0)
0(
0'
1B
1C
0D
0>
0=
0<
0;
0:
09
08
07
06
05
04
$end
#5000
1"
14
#10000
b1 1
0"
04
#15000
1"
14
#20000
1#
b10 1
0"
15
04
#20010
b1 $
1%
1=
1>
#25000
1"
14
b1 A
b1 E
b1 @
10
#30000
b11 1
0"
04
#30010
b10 $
0=
1<
#35000
1"
14
b10 A
b11 E
b11 @
1/
#40000
b100 1
0"
04
#40010
b11 $
1=
#45000
1"
14
b11 A
b110 E
b110 @
1D
00
1.
#50000
b101 1
0"
04
#50010
b1110 $
0=
1;
1:
#55000
1"
14
1?
b0 A
b10100 E
b10100 @
1&
0D
0/
1,
#60000
b1 2
b110 1
0"
04
#60010
b101 $
1=
0<
0:
#65000
1"
14
b1 A
b101 E
b101 @
0?
10
0,
0&
#70000
b111 1
0"
04
#70010
b10 $
0=
1<
0;
#75000
1"
14
b10 A
b111 E
b111 @
1/
#80000
b1000 1
0"
04
#80010
b1100111 $
1=
1;
18
17
#85000
1"
14
b11 A
b1101110 E
b1101110 @
1D
00
1-
1+
1*
#90000
b1001 1
0"
04
#90010
b100 $
0=
0<
08
07
#95000
1"
14
1?
b0 A
b1110010 E
b1110010 @
1&
0D
0.
0-
1,
#100000
b10 2
b1010 1
0"
04
#100010
b101 $
1=
#105000
1"
14
b1 A
b101 E
b101 @
0?
10
0/
1.
0,
0+
0*
0&
#110000
b1011 1
0"
04
#110010
b110 $
0=
1<
#115000
1"
14
b10 A
b1011 E
b1011 @
1/
0.
1-
#120000
b1100 1
0"
04
#120010
b11 $
1=
0;
#125000
1"
14
b11 A
b1110 E
b1110 @
1D
00
1.
#130000
b1101 1
0"
04
#130010
b110110 $
0=
1;
19
18
#135000
1"
14
1?
b0 A
b1000100 E
b1000100 @
1&
0D
0/
0-
1*
#140000
b11 2
b1110 1
0"
04
#145000
1"
14
b1 A
b110110 E
b110110 @
0?
1/
1,
1+
0*
0&
#150000
b1111 1
