Designs_old/sqrt/old/old_rtl/sqrt_calculator_old.v
module sqrt_calculator (
    input wire clk,
    input wire rst,
    input wire start,
    input wire [15:0] in,
    output reg [7:0] out,
    output reg error,
    output reg done
);

    reg [15:0] num;
    reg [7:0] guess;
    reg [3:0] iter;

    always @(posedge clk or posedge rst) begin
        if (rst) begin
            out <= 0;
            error <= 0;
            done <= 0;
            num <= 0;
            guess <= 0;
            iter <= 0;
        end else if (start) begin
            if (in[15] == 1) begin // Check if input is negative: Assuming 2's complement for input
                error <= 1;
                done <= 1;
            end else begin
                num <= in;
                guess <= 8'd1; // Initial guess
                iter <= 0;
                error <= 0;
                done <= 0;
            end
        end else if (!done) begin
            if (iter < 10) begin
                guess <= (guess + (num / guess)) >> 1; // Newton-Raphson method
                iter <= iter + 1;
            end else begin
                out <= guess;
                done <= 1;
            end
        end
    end

endmodule

Designs/sqrt/6_testbench_generator/testbench_in_eq_0.sv
`timescale 1ns/1ns

module test;

  logic clk;

  logic rst;

  logic start;

  logic [15:0] in;

  logic [7:0] out;

  logic error;

  logic done;


  // Device Under Test (DUT)

  sqrt_calculator dut(
    .clk(clk),
    .rst(rst),
    .start(start),
    .in(in),
    .out(out),
    .error(error),
    .done(done)
  );


  always #5 clk = ~clk;


  initial begin

    $dumpfile("sqrt_calculator_in_eq_0.vcd");

    $dumpvars(0, test);

    clk = 0;

    start = 0;

    in = 0;

    #10;

    in = 0;

    start = 1;

    #10 start = 0;

    #0 in = 0;

    #110;

    in = 0;

    start = 1;

    #10 start = 0;

    #0 in = 0;

    #110;

    in = 0;

    start = 1;

    #10 start = 0;

    #0 in = 0;

    #110;

    in = 0;

    start = 1;

    #10 start = 0;

    #0 in = 0;

    #110;

    in = 0;

    start = 1;

    #10 start = 0;

    #0 in = 0;

    #110;

    in = 0;

    start = 1;

    #10 start = 0;

    #0 in = 0;

    #110;

    in = 0;

    start = 1;

    #10 start = 0;

    #0 in = 0;

    #110;

    in = 0;

    start = 1;

    #10 start = 0;

    #0 in = 0;

    #110;

    in = 0;

    start = 1;

    #10 start = 0;

    #0 in = 0;

    #110;

    in = 0;

    start = 1;

    #10 start = 0;

    #0 in = 0;

    #110;

    in = 0;

    start = 1;

    #10 start = 0;

    #0 in = 0;

    #110;

    in = 0;

    start = 1;

    #10 start = 0;

    #0 in = 0;

    #110;

    in = 0;

    start = 1;

    #10 start = 0;

    #0 in = 0;

    #110;

    in = 0;

    start = 1;

    #10 start = 0;

    #0 in = 0;

    #110;

    in = 0;

    start = 1;

    #10 start = 0;

    #0 in = 0;

    #110;

    in = 0;

    start = 1;

    #10 start = 0;

    #0 in = 0;

    #110;

    in = 0;

    start = 1;

    #10 start = 0;

    #0 in = 0;

    #110;

    in = 0;

    start = 1;

    #10 start = 0;

    #0 in = 0;

    #110;

    in = 0;

    start = 1;

    #10 start = 0;

    #0 in = 0;

    #110;

    in = 0;

    start = 1;

    #10 start = 0;

    #0 in = 0;

    #110;

    in = 0;

    start = 1;

    #10 start = 0;

    #0 in = 0;

    #110;

    in = 0;

    start = 1;

    #10 start = 0;

    #0 in = 0;

    #110;

    in = 0;

    start = 1;

    #10 start = 0;

    #0 in = 0;

    #110;

    in = 0;

    start = 1;

    #10 start = 0;

    #0 in = 0;

    #110;

    in = 0;

    start = 1;

    #10 start = 0;

    #0 in = 0;

    #110;

    in = 0;

    start = 1;

    #10 start = 0;

    #0 in = 0;

    #110;

    in = 0;

    start = 1;

    #10 start = 0;

    #0 in = 0;

    #110;

    in = 0;

    start = 1;

    #10 start = 0;

    #0 in = 0;

    #110;

    in = 0;

    start = 1;

    #10 start = 0;

    #0 in = 0;

    #110;

    in = 0;

    start = 1;

    #10 start = 0;

    #0 in = 0;

    #110;

    in = 0;

    start = 1;

    #10 start = 0;

    #0 in = 0;

    #110;

    in = 0;

    start = 1;

    #10 start = 0;

    #0 in = 0;

    #110;

    in = 0;

    start = 1;

    #10 start = 0;

    #0 in = 0;

    #110;

    in = 0;

    start = 1;

    #10 start = 0;

    #0 in = 0;

    #110;

    in = 0;

    start = 1;

    #10 start = 0;

    #0 in = 0;

    #110;

    in = 0;

    start = 1;

    #10 start = 0;

    #0 in = 0;

    #110;

    in = 0;

    start = 1;

    #10 start = 0;

    #0 in = 0;

    #110;

    in = 0;

    start = 1;

    #10 start = 0;

    #0 in = 0;

    #110;

    in = 0;

    start = 1;

    #10 start = 0;

    #0 in = 0;

    #110;

    in = 0;

    start = 1;

    #10 start = 0;

    #0 in = 0;

    #110;

    in = 0;

    start = 1;

    #10 start = 0;

    #0 in = 0;

    #110;

    in = 0;

    start = 1;

    #10 start = 0;

    #0 in = 0;

    #110;

    in = 0;

    start = 1;

    #10 start = 0;

    #0 in = 0;

    #110;

    in = 0;

    start = 1;

    #10 start = 0;

    #0 in = 0;

    #110;

    in = 0;

    start = 1;

    #10 start = 0;

    #0 in = 0;

    #110;

    in = 0;

    start = 1;

    #10 start = 0;

    #0 in = 0;

    #110;

    in = 0;

    start = 1;

    #10 start = 0;

    #0 in = 0;

    #110;

    in = 0;

    start = 1;

    #10 start = 0;

    #0 in = 0;

    #110;

    in = 0;

    start = 1;

    #10 start = 0;

    #0 in = 0;

    #110;

    in = 0;

    start = 1;

    #10 start = 0;

    #0 in = 0;

    #110;

    in = 0;

    start = 1;

    #10 start = 0;

    #0 in = 0;

    #110;

    in = 0;

    start = 1;

    #10 start = 0;

    #0 in = 0;

    #110;

    in = 0;

    start = 1;

    #10 start = 0;

    #0 in = 0;

    #110;

    in = 0;

    start = 1;

    #10 start = 0;

    #0 in = 0;

    #110;

    in = 0;

    start = 1;

    #10 start = 0;

    #0 in = 0;

    #110;

    in = 0;

    start = 1;

    #10 start = 0;

    #0 in = 0;

    #110;

    in = 0;

    start = 1;

    #10 start = 0;

    #0 in = 0;

    #110;

    in = 0;

    start = 1;

    #10 start = 0;

    #0 in = 0;

    #110;

    in = 0;

    start = 1;

    #10 start = 0;

    #0 in = 0;

    #110;

    in = 0;

    start = 1;

    #10 start = 0;

    #0 in = 0;

    #110;

    in = 0;

    start = 1;

    #10 start = 0;

    #0 in = 0;

    #110;

    in = 0;

    start = 1;

    #10 start = 0;

    #0 in = 0;

    #110;

    in = 0;

    start = 1;

    #10 start = 0;

    #0 in = 0;

    #110;

    in = 0;

    start = 1;

    #10 start = 0;

    #0 in = 0;

    #110;

    in = 0;

    start = 1;

    #10 start = 0;

    #0 in = 0;

    #110;

    in = 0;

    start = 1;

    #10 start = 0;

    #0 in = 0;

    #110;

    in = 0;

    start = 1;

    #10 start = 0;

    #0 in = 0;

    #110;

    in = 0;

    start = 1;

    #10 start = 0;

    #0 in = 0;

    #110;

    in = 0;

    start = 1;

    #10 start = 0;

    #0 in = 0;

    #110;

    in = 0;

    start = 1;

    #10 start = 0;

    #0 in = 0;

    #110;

    in = 0;

    start = 1;

    #10 start = 0;

    #0 in = 0;

    #110;

    in = 0;

    start = 1;

    #10 start = 0;

    #0 in = 0;

    #110;

    in = 0;

    start = 1;

    #10 start = 0;

    #0 in = 0;

    #110;

    in = 0;

    start = 1;

    #10 start = 0;

    #0 in = 0;

    #110;

    in = 0;

    start = 1;

    #10 start = 0;

    #0 in = 0;

    #110;

    in = 0;

    start = 1;

    #10 start = 0;

    #0 in = 0;

    #110;

    in = 0;

    start = 1;

    #10 start = 0;

    #0 in = 0;

    #110;

    in = 0;

    start = 1;

    #10 start = 0;

    #0 in = 0;

    #110;

    in = 0;

    start = 1;

    #10 start = 0;

    #0 in = 0;

    #110;

    in = 0;

    start = 1;

    #10 start = 0;

    #0 in = 0;

    #110;

    in = 0;

    start = 1;

    #10 start = 0;

    #0 in = 0;

    #110;

    in = 0;

    start = 1;

    #10 start = 0;

    #0 in = 0;

    #110;

    in = 0;

    start = 1;

    #10 start = 0;

    #0 in = 0;

    #110;

    in = 0;

    start = 1;

    #10 start = 0;

    #0 in = 0;

    #110;

    #50;

    $finish;
  end
endmodule

Designs/sqrt/6_testbench_generator/sqrt_calculator_in_eq_0.vcd
$date
	Sat Aug 16 16:41:13 2025
$end
$version
	ModelSim Version 2019.4
$end
$timescale
	1ns
$end

$scope module test $end
$var reg 1 ! clk $end
$var reg 1 " rst $end
$var reg 1 # start $end
$var reg 16 $ in [15:0] $end
$var reg 8 % out [7:0] $end
$var reg 1 & error $end
$var reg 1 ' done $end

$scope module dut $end
$var wire 1 ( clk $end
$var wire 1 ) rst $end
$var wire 1 * start $end
$var wire 1 + in [15] $end
$var wire 1 , in [14] $end
$var wire 1 - in [13] $end
$var wire 1 . in [12] $end
$var wire 1 / in [11] $end
$var wire 1 0 in [10] $end
$var wire 1 1 in [9] $end
$var wire 1 2 in [8] $end
$var wire 1 3 in [7] $end
$var wire 1 4 in [6] $end
$var wire 1 5 in [5] $end
$var wire 1 6 in [4] $end
$var wire 1 7 in [3] $end
$var wire 1 8 in [2] $end
$var wire 1 9 in [1] $end
$var wire 1 : in [0] $end
$var reg 8 ; out [7:0] $end
$var reg 1 < error $end
$var reg 1 = done $end
$var reg 16 > num [15:0] $end
$var reg 8 ? guess [7:0] $end
$var reg 4 @ iter [3:0] $end
$upscope $end
$upscope $end
$enddefinitions $end
#0
$dumpvars
0!
x"
0#
b0 $
bx %
x&
x'
bx ;
x<
x=
bx >
bx ?
bx @
0:
09
08
07
06
05
04
03
02
01
00
0/
0.
0-
0,
0+
0*
x)
0(
$end
#5
1!
1(
#10
1#
0!
1*
0(
#15
1!
1(
b0 >
b1 ?
b0 @
0<
0=
0'
0&
#20
0#
0!
0*
0(
#25
1!
1(
b0 ?
b1 @
#30
0!
0(
#35
1!
1(
bx ?
b10 @
#40
0!
0(
#45
1!
1(
b11 @
#50
0!
0(
#55
1!
1(
b100 @
#60
0!
0(
#65
1!
1(
b101 @
#70
0!
0(
#75
1!
1(
b110 @
#80
0!
0(
#85
1!
1(
b111 @
#90
0!
0(
#95
1!
1(
b1000 @
#100
0!
0(
#105
1!
1(
b1001 @
#110
0!
0(
#115
1!
1(
b1010 @
#120
0!
0(
#125
1!
1(
1=
1'
#130
1#
0!
1*
0(
#135
1!
1(
b1 ?
b0 @
0=
0'
#140
0#
0!
0*
0(
#145
1!
1(
b0 ?
b1 @
#150
0!
0(
#155
1!
1(
bx ?
b10 @
#160
0!
0(
#165
1!
1(
b11 @
#170
0!
0(
#175
1!
1(
b100 @
#180
0!
0(
#185
1!
1(
b101 @
#190
0!
0(
#195
1!
1(
b110 @
#200
0!
0(
#205
1!
1(
b111 @
#210
0!
0(
#215
1!
1(
b1000 @
#220
0!
0(
#225
1!
1(
b1001 @
#230
0!
0(
#235
1!
1(
b1010 @
#240
0!
0(
#245
1!
1(
1=
1'
#250
1#
0!
1*
0(
#255
1!
1(
b1 ?
b0 @
0=
0'
#260
0#
0!
0*
0(
#265
1!
1(
b0 ?
b1 @
#270
0!
0(
#275
1!
1(
bx ?
b10 @
#280
0!
0(
#285
1!
1(
b11 @
#290
0!
0(
#295
1!
1(
b100 @
#300
0!
0(
#305
1!
1(
b101 @
#310
0!
0(
#315
1!
1(
b110 @
#320
0!
0(
#325
1!
1(
b111 @
#330
0!
0(
#335
1!
1(
b1000 @
#340
0!
0(
#345
1!
1(
b1001 @
#350
0!
0(
#355
1!
1(
b1010 @
#360
0!
0(
#365
1!
1(
1=
1'
#370
1#
0!
1*
0(
#375
1!
1(
b1 ?
b0 @
0=
0'
#380
0#
0!
0*
0(
#385
1!
1(
b0 ?
b1 @
#390
0!
0(
#395
1!
1(
bx ?
b10 @
#400
0!
0(
#405
1!
1(
b11 @
#410
0!
0(
#415
1!
1(
b100 @
#420
0!
0(
#425
1!
1(
b101 @
#430
0!
0(
#435
1!
1(
b110 @
#440
0!
0(
#445
1!
1(
b111 @
#450
0!
0(
#455
1!
1(
b1000 @
#460
0!
0(
#465
1!
1(
b1001 @
#470
0!
0(
#475
1!
1(
b1010 @
#480
0!
0(
#485
1!
1(
1=
1'
#490
1#
0!
1*
0(
#495
1!
1(
b1 ?
b0 @
0=
0'
#500
0#
0!
0*
0(
#505
1!
1(
b0 ?
b1 @
#510
0!
0(
#515
1!
1(
bx ?
b10 @
#520
0!
0(
#525
1!
1(
b11 @
#530
0!
0(
#535
1!
1(
b100 @
#540
0!
0(
#545
1!
1(
b101 @
#550
0!
0(
#555
1!
1(
b110 @
#560
0!
0(
#565
1!
1(
b111 @
#570
0!
0(
#575
1!
1(
b1000 @
#580
0!
0(
#585
1!
1(
b1001 @
#590
0!
0(
#595
1!
1(
b1010 @
#600
0!
0(
#605
1!
1(
1=
1'
#610
1#
0!
1*
0(
#615
1!
1(
b1 ?
b0 @
0=
0'
#620
0#
0!
0*
0(
#625
1!
1(
b0 ?
b1 @
#630
0!
0(
#635
1!
1(
bx ?
b10 @
#640
0!
0(
#645
1!
1(
b11 @
#650
0!
0(
#655
1!
1(
b100 @
#660
0!
0(
#665
1!
1(
b101 @
#670
0!
0(
#675
1!
1(
b110 @
#680
0!
0(
#685
1!
1(
b111 @
#690
0!
0(
#695
1!
1(
b1000 @
#700
0!
0(
#705
1!
1(
b1001 @
#710
0!
0(
#715
1!
1(
b1010 @
#720
0!
0(
#725
1!
1(
1=
1'
#730
1#
0!
1*
0(
#735
1!
1(
b1 ?
b0 @
0=
0'
#740
0#
0!
0*
0(
#745
1!
1(
b0 ?
b1 @
#750
0!
0(
#755
1!
1(
bx ?
b10 @
#760
0!
0(
#765
1!
1(
b11 @
#770
0!
0(
#775
1!
1(
b100 @
#780
0!
0(
#785
1!
1(
b101 @
#790
0!
0(
#795
1!
1(
b110 @
#800
0!
0(
#805
1!
1(
b111 @
#810
0!
0(
#815
1!
1(
b1000 @
#820
0!
0(
#825
1!
1(
b1001 @
#830
0!
0(
#835
1!
1(
b1010 @
#840
0!
0(
#845
1!
1(
1=
1'
#850
1#
0!
1*
0(
#855
1!
1(
b1 ?
b0 @
0=
0'
#860
0#
0!
0*
0(
#865
1!
1(
b0 ?
b1 @
#870
0!
0(
#875
1!
1(
bx ?
b10 @
#880
0!
0(
#885
1!
1(
b11 @
#890
0!
0(
#895
1!
1(
b100 @
#900
0!
0(
#905
1!
1(
b101 @
#910
0!
0(
#915
1!
1(
b110 @
#920
0!
0(
#925
1!
1(
b111 @
#930
0!
0(
#935
1!
1(
b1000 @
#940
0!
0(
#945
1!
1(
b1001 @
#950
0!
0(
#955
1!
1(
b1010 @
#960
0!
0(
#965
1!
1(
1=
1'
#970
1#
0!
1*
0(
#975
1!
1(
b1 ?
b0 @
0=
0'
#980
0#
0!
0*
0(
#985
1!
1(
b0 ?
b1 @
#990
0!
0(
#995
1!
1(
bx ?
b10 @
#1000
0!
0(
#1005
1!
1(
b11 @
#1010
0!
0(
#1015
1!
1(
b100 @
#1020
0!
0(
#1025
1!
1(
b101 @
#1030
0!
0(
#1035
1!
1(
b110 @
#1040
0!
0(
#1045
1!
1(
b111 @
#1050
0!
0(
#1055
1!
1(
b1000 @
#1060
0!
0(
#1065
1!
1(
b1001 @
#1070
0!
0(
#1075
1!
1(
b1010 @
#1080
0!
0(
#1085
1!
1(
1=
1'
#1090
1#
0!
1*
0(
#1095
1!
1(
b1 ?
b0 @
0=
0'
#1100
0#
0!
0*
0(
#1105
1!
1(
b0 ?
b1 @
#1110
0!
0(
#1115
1!
1(
bx ?
b10 @
#1120
0!
0(
#1125
1!
1(
b11 @
#1130
0!
0(
#1135
1!
1(
b100 @
#1140
0!
0(
#1145
1!
1(
b101 @
#1150
0!
0(
#1155
1!
1(
b110 @
#1160
0!
0(
#1165
1!
1(
b111 @
#1170
0!
0(
#1175
1!
1(
b1000 @
#1180
0!
0(
#1185
1!
1(
b1001 @
#1190
0!
0(
#1195
1!
1(
b1010 @
#1200
0!
0(
#1205
1!
1(
1=
1'
#1210
1#
0!
1*
0(
#1215
1!
1(
b1 ?
b0 @
0=
0'
#1220
0#
0!
0*
0(
#1225
1!
1(
b0 ?
b1 @
#1230
0!
0(
#1235
1!
1(
bx ?
b10 @
#1240
0!
0(
#1245
1!
1(
b11 @
#1250
0!
0(
#1255
1!
1(
b100 @
#1260
0!
0(
#1265
1!
1(
b101 @
#1270
0!
0(
#1275
1!
1(
b110 @
#1280
0!
0(
#1285
1!
1(
b111 @
#1290
0!
0(
#1295
1!
1(
b1000 @
#1300
0!
0(
#1305
1!
1(
b1001 @
#1310
0!
0(
#1315
1!
1(
b1010 @
#1320
0!
0(
#1325
1!
1(
1=
1'
#1330
1#
0!
1*
0(
#1335
1!
1(
b1 ?
b0 @
0=
0'
#1340
0#
0!
0*
0(
#1345
1!
1(
b0 ?
b1 @
#1350
0!
0(
#1355
1!
1(
bx ?
b10 @
#1360
0!
0(
#1365
1!
1(
b11 @
#1370
0!
0(
#1375
1!
1(
b100 @
#1380
0!
0(
#1385
1!
1(
b101 @
#1390
0!
0(
#1395
1!
1(
b110 @
#1400
0!
0(
#1405
1!
1(
b111 @
#1410
0!
0(
#1415
1!
1(
b1000 @
#1420
0!
0(
#1425
1!
1(
b1001 @
#1430
0!
0(
#1435
1!
1(
b1010 @
#1440
0!
0(
#1445
1!
1(
1=
1'
#1450
1#
0!
1*
0(
#1455
1!
1(
b1 ?
b0 @
0=
0'
#1460
0#
0!
0*
0(
#1465
1!
1(
b0 ?
b1 @
#1470
0!
0(
#1475
1!
1(
bx ?
b10 @
#1480
0!
0(
#1485
1!
1(
b11 @
#1490
0!
0(
#1495
1!
1(
b100 @
#1500
0!
0(
#1505
1!
1(
b101 @
#1510
0!
0(
#1515
1!
1(
b110 @
#1520
0!
0(
#1525
1!
1(
b111 @
#1530
0!
0(
#1535
1!
1(
b1000 @
#1540
0!
0(
#1545
1!
1(
b1001 @
#1550
0!
0(
#1555
1!
1(
b1010 @
#1560
0!
0(
#1565
1!
1(
1=
1'
#1570
1#
0!
1*
0(
#1575
1!
1(
b1 ?
b0 @
0=
0'
#1580
0#
0!
0*
0(
#1585
1!
1(
b0 ?
b1 @
#1590
0!
0(
#1595
1!
1(
bx ?
b10 @
#1600
0!
0(
#1605
1!
1(
b11 @
#1610
0!
0(
#1615
1!
1(
b100 @
#1620
0!
0(
#1625
1!
1(
b101 @
#1630
0!
0(
#1635
1!
1(
b110 @
#1640
0!
0(
#1645
1!
1(
b111 @
#1650
0!
0(
#1655
1!
1(
b1000 @
#1660
0!
0(
#1665
1!
1(
b1001 @
#1670
0!
0(
#1675
1!
1(
b1010 @
#1680
0!
0(
#1685
1!
1(
1=
1'
#1690
1#
0!
1*
0(
#1695
1!
1(
b1 ?
b0 @
0=
0'
#1700
0#
0!
0*
0(
#1705
1!
1(
b0 ?
b1 @
#1710
0!
0(
#1715
1!
1(
bx ?
b10 @
#1720
0!
0(
#1725
1!
1(
b11 @
#1730
0!
0(
#1735
1!
1(
b100 @
#1740
0!
0(
#1745
1!
1(
b101 @
#1750
0!
0(
#1755
1!
1(
b110 @
#1760
0!
0(
#1765
1!
1(
b111 @
#1770
0!
0(
#1775
1!
1(
b1000 @
#1780
0!
0(
#1785
1!
1(
b1001 @
#1790
0!
0(
#1795
1!
1(
b1010 @
#1800
0!
0(
#1805
1!
1(
1=
1'
#1810
1#
0!
1*
0(
#1815
1!
1(
b1 ?
b0 @
0=
0'
#1820
0#
0!
0*
0(
#1825
1!
1(
b0 ?
b1 @
#1830
0!
0(
#1835
1!
1(
bx ?
b10 @
#1840
0!
0(
#1845
1!
1(
b11 @
#1850
0!
0(
#1855
1!
1(
b100 @
#1860
0!
0(
#1865
1!
1(
b101 @
#1870
0!
0(
#1875
1!
1(
b110 @
#1880
0!
0(
#1885
1!
1(
b111 @
#1890
0!
0(
#1895
1!
1(
b1000 @
#1900
0!
0(
#1905
1!
1(
b1001 @
#1910
0!
0(
#1915
1!
1(
b1010 @
#1920
0!
0(
#1925
1!
1(
1=
1'
#1930
1#
0!
1*
0(
#1935
1!
1(
b1 ?
b0 @
0=
0'
#1940
0#
0!
0*
0(
#1945
1!
1(
b0 ?
b1 @
#1950
0!
0(
#1955
1!
1(
bx ?
b10 @
#1960
0!
0(
#1965
1!
1(
b11 @
#1970
0!
0(
#1975
1!
1(
b100 @
#1980
0!
0(
#1985
1!
1(
b101 @
#1990
0!
0(
#1995
1!
1(
b110 @
#2000
0!
0(
#2005
1!
1(
b111 @
#2010
0!
0(
#2015
1!
1(
b1000 @
#2020
0!
0(
#2025
1!
1(
b1001 @
#2030
0!
0(
#2035
1!
1(
b1010 @
#2040
0!
0(
#2045
1!
1(
1=
1'
#2050
1#
0!
1*
0(
#2055
1!
1(
b1 ?
b0 @
0=
0'
#2060
0#
0!
0*
0(
#2065
1!
1(
b0 ?
b1 @
#2070
0!
0(
#2075
1!
1(
bx ?
b10 @
#2080
0!
0(
#2085
1!
1(
b11 @
#2090
0!
0(
#2095
1!
1(
b100 @
#2100
0!
0(
#2105
1!
1(
b101 @
#2110
0!
0(
#2115
1!
1(
b110 @
#2120
0!
0(
#2125
1!
1(
b111 @
#2130
0!
0(
#2135
1!
1(
b1000 @
#2140
0!
0(
#2145
1!
1(
b1001 @
#2150
0!
0(
#2155
1!
1(
b1010 @
#2160
0!
0(
#2165
1!
1(
1=
1'
#2170
1#
0!
1*
0(
#2175
1!
1(
b1 ?
b0 @
0=
0'
#2180
0#
0!
0*
0(
#2185
1!
1(
b0 ?
b1 @
#2190
0!
0(
#2195
1!
1(
bx ?
b10 @
#2200
0!
0(
#2205
1!
1(
b11 @
#2210
0!
0(
#2215
1!
1(
b100 @
#2220
0!
0(
#2225
1!
1(
b101 @
#2230
0!
0(
#2235
1!
1(
b110 @
#2240
0!
0(
#2245
1!
1(
b111 @
#2250
0!
0(
#2255
1!
1(
b1000 @
#2260
0!
0(
#2265
1!
1(
b1001 @
#2270
0!
0(
#2275
1!
1(
b1010 @
#2280
0!
0(
#2285
1!
1(
1=
1'
#2290
1#
0!
1*
0(
#2295
1!
1(
b1 ?
b0 @
0=
0'
#2300
0#
0!
0*
0(
#2305
1!
1(
b0 ?
b1 @
#2310
0!
0(
#2315
1!
1(
bx ?
b10 @
#2320
0!
0(
#2325
1!
1(
b11 @
#2330
0!
0(
#2335
1!
1(
b100 @
#2340
0!
0(
#2345
1!
1(
b101 @
#2350
0!
0(
#2355
1!
1(
b110 @
#2360
0!
0(
#2365
1!
1(
b111 @
#2370
0!
0(
#2375
1!
1(
b1000 @
#2380
0!
0(
#2385
1!
1(
b1001 @
#2390
0!
0(
#2395
1!
1(
b1010 @
#2400
0!
0(
#2405
1!
1(
1=
1'
#2410
1#
0!
1*
0(
#2415
1!
1(
b1 ?
b0 @
0=
0'
#2420
0#
0!
0*
0(
#2425
1!
1(
b0 ?
b1 @
#2430
0!
0(
#2435
1!
1(
bx ?
b10 @
#2440
0!
0(
#2445
1!
1(
b11 @
#2450
0!
0(
#2455
1!
1(
b100 @
#2460
0!
0(
#2465
1!
1(
b101 @
#2470
0!
0(
#2475
1!
1(
b110 @
#2480
0!
0(
#2485
1!
1(
b111 @
#2490
0!
0(
#2495
1!
1(
b1000 @
#2500
0!
0(
#2505
1!
1(
b1001 @
#2510
0!
0(
#2515
1!
1(
b1010 @
#2520
0!
0(
#2525
1!
1(
1=
1'
#2530
1#
0!
1*
0(
#2535
1!
1(
b1 ?
b0 @
0=
0'
#2540
0#
0!
0*
0(
#2545
1!
1(
b0 ?
b1 @
#2550
0!
0(
#2555
1!
1(
bx ?
b10 @
#2560
0!
0(
#2565
1!
1(
b11 @
#2570
0!
0(
#2575
1!
1(
b100 @
#2580
0!
0(
#2585
1!
1(
b101 @
#2590
0!
0(
#2595
1!
1(
b110 @
#2600
0!
0(
#2605
1!
1(
b111 @
#2610
0!
0(
#2615
1!
1(
b1000 @
#2620
0!
0(
#2625
1!
1(
b1001 @
#2630
0!
0(
#2635
1!
1(
b1010 @
#2640
0!
0(
#2645
1!
1(
1=
1'
#2650
1#
0!
1*
0(
#2655
1!
1(
b1 ?
b0 @
0=
0'
#2660
0#
0!
0*
0(
#2665
1!
1(
b0 ?
b1 @
#2670
0!
0(
#2675
1!
1(
bx ?
b10 @
#2680
0!
0(
#2685
1!
1(
b11 @
#2690
0!
0(
#2695
1!
1(
b100 @
#2700
0!
0(
#2705
1!
1(
b101 @
#2710
0!
0(
#2715
1!
1(
b110 @
#2720
0!
0(
#2725
1!
1(
b111 @
#2730
0!
0(
#2735
1!
1(
b1000 @
#2740
0!
0(
#2745
1!
1(
b1001 @
#2750
0!
0(
#2755
1!
1(
b1010 @
#2760
0!
0(
#2765
1!
1(
1=
1'
#2770
1#
0!
1*
0(
#2775
1!
1(
b1 ?
b0 @
0=
0'
#2780
0#
0!
0*
0(
#2785
1!
1(
b0 ?
b1 @
#2790
0!
0(
#2795
1!
1(
bx ?
b10 @
#2800
0!
0(
#2805
1!
1(
b11 @
#2810
0!
0(
#2815
1!
1(
b100 @
#2820
0!
0(
#2825
1!
1(
b101 @
#2830
0!
0(
#2835
1!
1(
b110 @
#2840
0!
0(
#2845
1!
1(
b111 @
#2850
0!
0(
#2855
1!
1(
b1000 @
#2860
0!
0(
#2865
1!
1(
b1001 @
#2870
0!
0(
#2875
1!
1(
b1010 @
#2880
0!
0(
#2885
1!
1(
1=
1'
#2890
1#
0!
1*
0(
#2895
1!
1(
b1 ?
b0 @
0=
0'
#2900
0#
0!
0*
0(
#2905
1!
1(
b0 ?
b1 @
#2910
0!
0(
#2915
1!
1(
bx ?
b10 @
#2920
0!
0(
#2925
1!
1(
b11 @
#2930
0!
0(
#2935
1!
1(
b100 @
#2940
0!
0(
#2945
1!
1(
b101 @
#2950
0!
0(
#2955
1!
1(
b110 @
#2960
0!
0(
#2965
1!
1(
b111 @
#2970
0!
0(
#2975
1!
1(
b1000 @
#2980
0!
0(
#2985
1!
1(
b1001 @
#2990
0!
0(
#2995
1!
1(
b1010 @
#3000
0!
0(
#3005
1!
1(
1=
1'
#3010
1#
0!
1*
0(
#3015
1!
1(
b1 ?
b0 @
0=
0'
#3020
0#
0!
0*
0(
#3025
1!
1(
b0 ?
b1 @
#3030
0!
0(
#3035
1!
1(
bx ?
b10 @
#3040
0!
0(
#3045
1!
1(
b11 @
#3050
0!
0(
#3055
1!
1(
b100 @
#3060
0!
0(
#3065
1!
1(
b101 @
#3070
0!
0(
#3075
1!
1(
b110 @
#3080
0!
0(
#3085
1!
1(
b111 @
#3090
0!
0(
#3095
1!
1(
b1000 @
#3100
0!
0(
#3105
1!
1(
b1001 @
#3110
0!
0(
#3115
1!
1(
b1010 @
#3120
0!
0(
#3125
1!
1(
1=
1'
#3130
1#
0!
1*
0(
#3135
1!
1(
b1 ?
b0 @
0=
0'
#3140
0#
0!
0*
0(
#3145
1!
1(
b0 ?
b1 @
#3150
0!
0(
#3155
1!
1(
bx ?
b10 @
#3160
0!
0(
#3165
1!
1(
b11 @
#3170
0!
0(
#3175
1!
1(
b100 @
#3180
0!
0(
#3185
1!
1(
b101 @
#3190
0!
0(
#3195
1!
1(
b110 @
#3200
0!
0(
#3205
1!
1(
b111 @
#3210
0!
0(
#3215
1!
1(
b1000 @
#3220
0!
0(
#3225
1!
1(
b1001 @
#3230
0!
0(
#3235
1!
1(
b1010 @
#3240
0!
0(
#3245
1!
1(
1=
1'
#3250
1#
0!
1*
0(
#3255
1!
1(
b1 ?
b0 @
0=
0'
#3260
0#
0!
0*
0(
#3265
1!
1(
b0 ?
b1 @
#3270
0!
0(
#3275
1!
1(
bx ?
b10 @
#3280
0!
0(
#3285
1!
1(
b11 @
#3290
0!
0(
#3295
1!
1(
b100 @
#3300
0!
0(
#3305
1!
1(
b101 @
#3310
0!
0(
#3315
1!
1(
b110 @
#3320
0!
0(
#3325
1!
1(
b111 @
#3330
0!
0(
#3335
1!
1(
b1000 @
#3340
0!
0(
#3345
1!
1(
b1001 @
#3350
0!
0(
#3355
1!
1(
b1010 @
#3360
0!
0(
#3365
1!
1(
1=
1'
#3370
1#
0!
1*
0(
#3375
1!
1(
b1 ?
b0 @
0=
0'
#3380
0#
0!
0*
0(
#3385
1!
1(
b0 ?
b1 @
#3390
0!
0(
#3395
1!
1(
bx ?
b10 @
#3400
0!
0(
#3405
1!
1(
b11 @
#3410
0!
0(
#3415
1!
1(
b100 @
#3420
0!
0(
#3425
1!
1(
b101 @
#3430
0!
0(
#3435
1!
1(
b110 @
#3440
0!
0(
#3445
1!
1(
b111 @
#3450
0!
0(
#3455
1!
1(
b1000 @
#3460
0!
0(
#3465
1!
1(
b1001 @
#3470
0!
0(
#3475
1!
1(
b1010 @
#3480
0!
0(
#3485
1!
1(
1=
1'
#3490
1#
0!
1*
0(
#3495
1!
1(
b1 ?
b0 @
0=
0'
#3500
0#
0!
0*
0(
#3505
1!
1(
b0 ?
b1 @
#3510
0!
0(
#3515
1!
1(
bx ?
b10 @
#3520
0!
0(
#3525
1!
1(
b11 @
#3530
0!
0(
#3535
1!
1(
b100 @
#3540
0!
0(
#3545
1!
1(
b101 @
#3550
0!
0(
#3555
1!
1(
b110 @
#3560
0!
0(
#3565
1!
1(
b111 @
#3570
0!
0(
#3575
1!
1(
b1000 @
#3580
0!
0(
#3585
1!
1(
b1001 @
#3590
0!
0(
#3595
1!
1(
b1010 @
#3600
0!
0(
#3605
1!
1(
1=
1'
#3610
1#
0!
1*
0(
#3615
1!
1(
b1 ?
b0 @
0=
0'
#3620
0#
0!
0*
0(
#3625
1!
1(
b0 ?
b1 @
#3630
0!
0(
#3635
1!
1(
bx ?
b10 @
#3640
0!
0(
#3645
1!
1(
b11 @
#3650
0!
0(
#3655
1!
1(
b100 @
#3660
0!
0(
#3665
1!
1(
b101 @
#3670
0!
0(
#3675
1!
1(
b110 @
#3680
0!
0(
#3685
1!
1(
b111 @
#3690
0!
0(
#3695
1!
1(
b1000 @
