Designs/mutex/rtl/mutex_f_posflag.v
module mutex(
    input wire clk,
    input wire [15:0] in,
    output reg positive_flag,
    output reg negative_flag
);

    always @(posedge clk) begin
        if (in[15] == 1) begin // Check if MSB is 1 (negative number in 2's complement)
            positive_flag = 0;
            negative_flag = 1;
        end else if (in == 16'd0) begin // Check if input is zero
            positive_flag = 0;
            negative_flag = 0;
        end else begin
            positive_flag = 0;
            negative_flag = 0;
        end
    end

endmodule

Designs/mutex/tb/tb_fp.v
module mutex_tb;
    reg clk;
    reg [15:0] in;
    wire positive_flag;
    wire negative_flag;

    mutex uut (
        .clk(clk),
        .in(in),
        .positive_flag(positive_flag),
        .negative_flag(negative_flag)
    );

    always #5  clk = ~clk; // Clock with 10 time unit period

    initial begin
        $dumpfile("fault_pos.vcd");
        $dumpvars(0, mutex_tb);
        
        //Initial 
        clk = 0; 
        in = 0;
        #10 

        // Test case 1: Positive number
        in = 16'd10;
        #10 ;
        $display("Input: %d, Positive: %b, Negative: %b", in, positive_flag, negative_flag);
        
        // Test case 2: Negative number
        in = -16'd5;
        #10 ;
        $display("Input: %d, Positive: %b, Negative: %b", in, positive_flag, negative_flag);
        
        // Test case 3: Zero
        in = 16'd0;
        #10 ;
        $display("Input: %d, Positive: %b, Negative: %b", in, positive_flag, negative_flag);
        
        // Test case 4: Random positive number
        in = 16'd12345;
        #10 ;
        $display("Input: %d, Positive: %b, Negative: %b", in, positive_flag, negative_flag);
        
        // Test case 5: Random negative number
        in = -16'd12345;
        #10 ;
        $display("Input: %d, Positive: %b, Negative: %b", in, positive_flag, negative_flag);
        
        // Test case 6: Another random positive number
        in = 16'd32767;
        #10 ;
        $display("Input: %d, Positive: %b, Negative: %b", in, positive_flag, negative_flag);
        
        // Test case 7: Another random negative number
        in = -16'd32768;
        #10 ;
        $display("Input: %d, Positive: %b, Negative: %b", in, positive_flag, negative_flag);

        #20 $finish;
    end
endmodule

Designs/mutex/traces/fault_pos.vcd
$date
	Mon Mar 24 14:01:38 2025
$end
$version
	ModelSim Version 2019.4
$end
$timescale
	1ns
$end

$scope module mutex_tb $end
$var reg 1 ! clk $end
$var reg 16 " in [15:0] $end
$var wire 1 # positive_flag $end
$var wire 1 $ negative_flag $end

$scope module uut $end
$var wire 1 % clk $end
$var wire 1 & in [15] $end
$var wire 1 ' in [14] $end
$var wire 1 ( in [13] $end
$var wire 1 ) in [12] $end
$var wire 1 * in [11] $end
$var wire 1 + in [10] $end
$var wire 1 , in [9] $end
$var wire 1 - in [8] $end
$var wire 1 . in [7] $end
$var wire 1 / in [6] $end
$var wire 1 0 in [5] $end
$var wire 1 1 in [4] $end
$var wire 1 2 in [3] $end
$var wire 1 3 in [2] $end
$var wire 1 4 in [1] $end
$var wire 1 5 in [0] $end
$var reg 1 6 positive_flag $end
$var reg 1 7 negative_flag $end
$upscope $end
$upscope $end
$enddefinitions $end
#0
$dumpvars
0!
b0 "
x6
x7
x#
x$
05
04
03
02
01
00
0/
0.
0-
0,
0+
0*
0)
0(
0'
0&
0%
$end
#5
1!
1%
06
07
0#
0$
#10
b1010 "
0!
14
12
0%
#15
1!
1%
#20
b1111111111111011 "
0!
15
11
10
1/
1.
1-
1,
1+
1*
1)
1(
1'
1&
0%
#25
1!
1%
17
1$
#30
b0 "
0!
05
04
02
01
00
0/
0.
0-
0,
0+
0*
0)
0(
0'
0&
0%
#35
1!
1%
07
0$
#40
b11000000111001 "
0!
15
12
11
10
1)
1(
0%
#45
1!
1%
#50
b1100111111000111 "
0!
14
13
02
01
00
1/
1.
1-
1,
1+
1*
0)
0(
1'
1&
0%
#55
1!
1%
17
1$
#60
b111111111111111 "
0!
12
11
10
1)
1(
0&
0%
#65
1!
1%
07
0$
#70
b1000000000000000 "
0!
05
04
03
02
01
00
0/
0.
0-
0,
0+
0*
0)
0(
0'
1&
0%
#75
1!
1%
17
1$
